<?xml version='1.0' encoding='utf-8'?>
<timetable station="Berlin Hermannstraße" eva="8089105">
  <s id="-2620349068839419937-2509040741-9" eva="8089105">
    <ar ct="2509040800" l="41" />
    <dp ct="2509040800" l="41" />
  </s>
  <s id="-5153515271206664391-2509040815-17" eva="8089105">
    <ar ct="2509040851" l="42" />
    <dp ct="2509040851" l="42" />
  </s>
  <s id="8946632205067833719-2509040814-5" eva="8089105">
    <ar ct="2509040824" l="41" />
    <dp ct="2509040824" l="41" />
  </s>
  <s id="3909321172287427276-2509040736-12" eva="8089105">
    <ar ct="2509040759" l="46" />
    <dp ct="2509040800" l="46" />
  </s>
  <s id="886488211225662463-2509040721-12" eva="8089105">
    <ar ct="2509040758" l="46" />
    <dp ct="2509040759" l="46" />
  </s>
</timetable>