<?xml version='1.0' encoding='utf-8'?>
<timetable station="Berlin-Tiergarten" eva="8089091">
  <s id="-6637773591391591206-2509070825-4" eva="8089091">
    <ar ct="2509070830" l="3" />
    <dp ct="2509070831" l="3" />
  </s>
  <s id="4599888517185600270-2509070845-4" eva="8089091">
    <ar ct="2509070850" l="3" />
    <dp ct="2509070851" l="3" />
  </s>
  <s id="-1895862484362575289-2509070845-20" eva="8089091">
    <m id="r2436847" t="h" from="2508312100" to="2509150700" cat="Information" ts="2508302307" ts-tts="25-09-06 23:16:03.182" pr="1" />
    <ar ct="2509070933" l="3" />
    <dp ct="2509070934" l="3" />
  </s>
  <s id="-514507170410561029-2509070808-10" eva="8089091">
    <ar ct="2509070828" l="5" />
    <dp ct="2509070829" l="5" />
  </s>
</timetable>