<?xml version='1.0' encoding='utf-8'?>
<timetable station="Berlin-Staaken" eva="8013021">
  <s id="1499828262057328339-2509040907-3" eva="8013021">
    <ar ct="2509040917" l="8" />
    <dp ct="2509040916" l="8" />
  </s>
  <s id="5011651600290050495-2509040835-10" eva="8013021">
    <ar ct="2509040921" l="21">
      <m id="r23878898" t="d" c="43" ts="2509040838" ts-tts="25-09-04 08:38:31.288" />
      <m id="r23878900" t="d" c="43" ts="2509040838" ts-tts="25-09-04 08:38:31.288" />
    </ar>
    <dp ct="2509040922" l="21">
      <m id="r23878898" t="d" c="43" ts="2509040838" ts-tts="25-09-04 08:38:31.288" />
      <m id="r23878900" t="d" c="43" ts="2509040838" ts-tts="25-09-04 08:38:31.288" />
    </dp>
  </s>
  <s id="-4462161906458628689-2509040910-4" eva="8013021">
    <ar ct="2509040933" l="21">
      <m id="r23883239" t="d" c="43" ts="2509040914" ts-tts="25-09-04 09:14:44.249" />
      <m id="r23883241" t="d" c="43" ts="2509040914" ts-tts="25-09-04 09:14:44.249" />
    </ar>
    <dp ct="2509040934" l="21">
      <m id="r23883239" t="d" c="43" ts="2509040914" ts-tts="25-09-04 09:14:44.249" />
      <m id="r23883241" t="d" c="43" ts="2509040914" ts-tts="25-09-04 09:14:44.249" />
    </dp>
  </s>
  <s id="8067495932162376830-2509040714-19" eva="8013021">
    <ar ct="2509040916" l="4" />
    <dp ct="2509040917" l="4" />
  </s>
</timetable>