<?xml version='1.0' encoding='utf-8'?>
<timetable station="Berlin Olympiastadion" eva="8089330">
  <s id="-8834954959424891019-2509061757-4" eva="8089330">
    <m id="r2436847" t="h" from="2508312100" to="2509150700" cat="Information" ts="2508302307" ts-tts="25-09-05 23:16:03.415" pr="1" />
  </s>
  <s id="-4485924743432221069-2509061737-4" eva="8089330">
    <m id="r2436847" t="h" from="2508312100" to="2509150700" cat="Information" ts="2508302307" ts-tts="25-09-05 23:16:03.415" pr="1" />
  </s>
  <s id="-8430692406790002316-2509061717-4" eva="8089330">
    <m id="r2436847" t="h" from="2508312100" to="2509150700" cat="Information" ts="2508302307" ts-tts="25-09-05 23:16:03.415" pr="1" />
  </s>
  <s id="599718064214426284-2509061749-27" eva="8089330">
    <m id="r2436847" t="h" from="2508312100" to="2509150700" cat="Information" ts="2508302307" ts-tts="25-09-05 23:16:03.415" pr="1" />
  </s>
  <s id="7064840669338736142-2509061729-27" eva="8089330">
    <m id="r2436847" t="h" from="2508312100" to="2509150700" cat="Information" ts="2508302307" ts-tts="25-09-05 23:16:03.415" pr="1" />
  </s>
  <s id="-6408243004757674637-2509061709-27" eva="8089330">
    <m id="r2436847" t="h" from="2508312100" to="2509150700" cat="Information" ts="2508302307" ts-tts="25-09-05 23:16:03.415" pr="1" />
  </s>
  <s id="6805005977943824336-2509061707-4" eva="8089330">
    <m id="r2436847" t="h" from="2508312100" to="2509150700" cat="Information" ts="2508302307" ts-tts="25-09-05 23:16:03.415" pr="1" />
  </s>
  <s id="5183786826876065133-2509061745-27" eva="8089330">
    <m id="r2436847" t="h" from="2508312100" to="2509150700" cat="Information" ts="2508302307" ts-tts="25-09-05 23:16:03.414" pr="1" />
  </s>
  <s id="-7877308287806187433-2509061725-27" eva="8089330">
    <m id="r2436847" t="h" from="2508312100" to="2509150700" cat="Information" ts="2508302307" ts-tts="25-09-05 23:16:03.414" pr="1" />
  </s>
  <s id="-769611413363731020-2509061705-27" eva="8089330">
    <m id="r2436847" t="h" from="2508312100" to="2509150700" cat="Information" ts="2508302307" ts-tts="25-09-05 23:16:03.414" pr="1" />
  </s>
  <s id="-6138468782757552192-2509061747-4" eva="8089330">
    <m id="r2436847" t="h" from="2508312100" to="2509150700" cat="Information" ts="2508302307" ts-tts="25-09-05 23:16:03.414" pr="1" />
  </s>
  <s id="-795186342634878573-2509061727-4" eva="8089330">
    <m id="r2436847" t="h" from="2508312100" to="2509150700" cat="Information" ts="2508302307" ts-tts="25-09-05 23:16:03.414" pr="1" />
  </s>
  <s id="4929082008786566995-2509060017-4" eva="8089330">
    <m id="r2436847" t="h" from="2508312100" to="2509150700" cat="Information" ts="2508302307" ts-tts="25-09-05 23:16:03.415" pr="1" />
    <ar cpth="" ct="2509060025" cs="c" clt="2509060027" l="9" />
    <dp cpth="Berlin Ostbahnhof (S)|Berlin Warschauer Straße|Berlin-Lichtenberg (S)" ct="2509060025" cs="c" clt="2509060027" l="9" />
  </s>
  <s id="3201377494826907730-2509060009-27" eva="8089330">
    <m id="r2436847" t="h" from="2508312100" to="2509150700" cat="Information" ts="2508302307" ts-tts="25-09-05 23:16:03.415" pr="1" />
    <ar ct="2509060122" l="9" />
    <dp ct="2509060122" l="9" />
  </s>
</timetable>