<?xml version='1.0' encoding='utf-8'?>
<timetable station="Berlin Baumschulenweg">
  <s id="-3331720145990329514-2509032044-4">
    <tl f="S" t="p" o="08" c="S" n="47153" />
    <ar pt="2509032051" pp="5" l="47" ppth="Berlin Hermannstraße|Berlin-Neukölln|Berlin Köllnische Heide" />
    <dp pt="2509032053" pp="5" l="47" ppth="Berlin-Schöneweide (S)|Berlin-Oberspree|Berlin-Spindlersfeld" />
  </s>
  <s id="-6525081265256121967-2509032016-15">
    <tl f="S" t="p" o="08" c="S" n="46115" />
    <ar pt="2509032046" pp="5" l="46" ppth="Berlin Westend|Berlin Messe Nord/ZOB (Witzleben)|Berlin Westkreuz|Berlin-Halensee|Berlin Hohenzollerndamm|Berlin Heidelberger Platz|Berlin Bundesplatz|Berlin Innsbrucker Platz|Berlin-Schöneberg|Berlin Südkreuz (S)|Berlin-Tempelhof|Berlin Hermannstraße|Berlin-Neukölln|Berlin Köllnische Heide" />
    <dp pt="2509032048" pp="5" l="46" ppth="Berlin-Schöneweide (S)|Berlin-Johannisthal|Berlin-Adlershof|Berlin-Grünau|Eichwalde|Zeuthen|Wildau|Königs Wusterhausen" />
  </s>
  <s id="-2018257680111692461-2509031957-9">
    <tl f="S" t="p" o="08" c="S" n="45108" />
    <ar pt="2509032022" pp="4" l="45" ppth="Flughafen BER (S-Bahn)|Waßmannsdorf|Schönefeld(bei Berlin)|Berlin Grünbergallee|Berlin-Altglienicke|Berlin-Adlershof|Berlin-Johannisthal|Berlin-Schöneweide (S)" />
    <dp pt="2509032023" pp="4" l="45" ppth="Berlin Köllnische Heide|Berlin-Neukölln|Berlin Hermannstraße|Berlin-Tempelhof|Berlin Südkreuz (S)" />
  </s>
  <s id="2928566847908751412-2509031956-15">
    <tl f="S" t="p" o="08" c="S" n="46113" />
    <ar pt="2509032026" pp="5" l="46" ppth="Berlin Westend|Berlin Messe Nord/ZOB (Witzleben)|Berlin Westkreuz|Berlin-Halensee|Berlin Hohenzollerndamm|Berlin Heidelberger Platz|Berlin Bundesplatz|Berlin Innsbrucker Platz|Berlin-Schöneberg|Berlin Südkreuz (S)|Berlin-Tempelhof|Berlin Hermannstraße|Berlin-Neukölln|Berlin Köllnische Heide" />
    <dp pt="2509032028" pp="5" l="46" ppth="Berlin-Schöneweide (S)|Berlin-Johannisthal|Berlin-Adlershof|Berlin-Grünau|Eichwalde|Zeuthen|Wildau|Königs Wusterhausen" />
  </s>
  <s id="-3372160847542610988-2509032005-5">
    <tl f="S" t="p" o="08" c="S" n="8131" />
    <ar pt="2509032015" pp="3" l="8" ppth="Berlin Frankfurter Allee|Berlin Ostkreuz (S)|Berlin Treptower Park|Berlin Plänterwald" />
    <dp pt="2509032015" pp="3" l="8" ppth="Berlin-Schöneweide (S)|Berlin-Johannisthal|Berlin-Adlershof|Berlin-Grünau" />
  </s>
  <s id="5826395670101667647-2509031937-22">
    <tl f="S" t="p" o="08" c="S" n="9425" />
    <ar pt="2509032027" pp="3" l="9" ppth="Berlin-Spandau (S)|Berlin-Stresow|Berlin-Pichelsberg|Berlin Olympiastadion|Berlin Heerstraße|Berlin Messe Süd (Eichkamp)|Berlin Westkreuz|Berlin Charlottenburg (S)|Berlin Savignyplatz|Berlin Zoologischer Garten (S)|Berlin-Tiergarten|Berlin Bellevue|Berlin Hbf (S-Bahn)|Berlin Friedrichstraße (S)|Berlin Hackescher Markt|Berlin Alexanderplatz (S)|Berlin Jannowitzbrücke|Berlin Ostbahnhof (S)|Berlin Warschauer Straße|Berlin Treptower Park|Berlin Plänterwald" />
    <dp pt="2509032030" pp="3" l="9" ppth="Berlin-Schöneweide (S)|Berlin-Johannisthal|Berlin-Adlershof|Berlin-Altglienicke|Berlin Grünbergallee|Schönefeld(bei Berlin)|Waßmannsdorf|Flughafen BER (S-Bahn)" />
  </s>
  <s id="-2026375958010820325-2509032001-9">
    <tl f="S" t="p" o="08" c="S" n="46114" />
    <ar pt="2509032027" pp="4" l="46" ppth="Königs Wusterhausen|Wildau|Zeuthen|Eichwalde|Berlin-Grünau|Berlin-Adlershof|Berlin-Johannisthal|Berlin-Schöneweide (S)" />
    <dp pt="2509032028" pp="4" l="46" ppth="Berlin Köllnische Heide|Berlin-Neukölln|Berlin Hermannstraße|Berlin-Tempelhof|Berlin Südkreuz (S)|Berlin-Schöneberg|Berlin Innsbrucker Platz|Berlin Bundesplatz|Berlin Heidelberger Platz|Berlin Hohenzollerndamm|Berlin-Halensee|Berlin Westkreuz|Berlin Messe Nord/ZOB (Witzleben)|Berlin Westend" />
  </s>
  <s id="8328908288568990858-2509032008-2">
    <tl f="S" t="p" o="08" c="S" n="85600" />
    <ar pt="2509032010" pp="4" l="85" ppth="Berlin-Schöneweide (S)" />
    <dp pt="2509032010" pp="4" l="85" ppth="Berlin Plänterwald|Berlin Treptower Park|Berlin Ostkreuz (S)|Berlin Frankfurter Allee" />
  </s>
  <s id="-6494063628463585341-2509032025-5">
    <tl f="S" t="p" o="08" c="S" n="8133" />
    <ar pt="2509032035" pp="3" l="8" ppth="Berlin Frankfurter Allee|Berlin Ostkreuz (S)|Berlin Treptower Park|Berlin Plänterwald" />
    <dp pt="2509032035" pp="3" l="8" ppth="Berlin-Schöneweide (S)|Berlin-Johannisthal|Berlin-Adlershof|Berlin-Grünau" />
  </s>
  <s id="-8668241575767945069-2509032029-5">
    <tl f="S" t="p" o="08" c="S" n="8136" />
    <ar pt="2509032040" pp="4" l="8" ppth="Berlin-Grünau|Berlin-Adlershof|Berlin-Johannisthal|Berlin-Schöneweide (S)" />
    <dp pt="2509032040" pp="4" l="8" ppth="Berlin Plänterwald|Berlin Treptower Park|Berlin Ostkreuz (S)|Berlin Frankfurter Allee" />
  </s>
  <s id="6314911921651397174-2509032021-9">
    <tl f="S" t="p" o="08" c="S" n="46116" />
    <ar pt="2509032047" pp="4" l="46" ppth="Königs Wusterhausen|Wildau|Zeuthen|Eichwalde|Berlin-Grünau|Berlin-Adlershof|Berlin-Johannisthal|Berlin-Schöneweide (S)" />
    <dp pt="2509032048" pp="4" l="46" ppth="Berlin Köllnische Heide|Berlin-Neukölln|Berlin Hermannstraße|Berlin-Tempelhof|Berlin Südkreuz (S)|Berlin-Schöneberg|Berlin Innsbrucker Platz|Berlin Bundesplatz|Berlin Heidelberger Platz|Berlin Hohenzollerndamm|Berlin-Halensee|Berlin Westkreuz|Berlin Messe Nord/ZOB (Witzleben)|Berlin Westend" />
  </s>
  <s id="2592128871816375636-2509032035-5">
    <tl f="S" t="p" o="08" c="S" n="85603" />
    <ar pt="2509032045" pp="3" l="85" ppth="Berlin Frankfurter Allee|Berlin Ostkreuz (S)|Berlin Treptower Park|Berlin Plänterwald" />
    <dp pt="2509032045" pp="3" l="85" ppth="Berlin-Schöneweide (S)" />
  </s>
  <s id="-2208929733415379913-2509031955-5">
    <tl f="S" t="p" o="08" c="S" n="85599" />
    <ar pt="2509032005" pp="3" l="85" ppth="Berlin Frankfurter Allee|Berlin Ostkreuz (S)|Berlin Treptower Park|Berlin Plänterwald" />
    <dp pt="2509032005" pp="3" l="85" ppth="Berlin-Schöneweide (S)" />
  </s>
  <s id="-4489258971327999510-2509032009-9">
    <tl f="S" t="p" o="08" c="S" n="9128" />
    <ar pt="2509032035" pp="4" l="9" ppth="Flughafen BER (S-Bahn)|Waßmannsdorf|Schönefeld(bei Berlin)|Berlin Grünbergallee|Berlin-Altglienicke|Berlin-Adlershof|Berlin-Johannisthal|Berlin-Schöneweide (S)" />
    <dp pt="2509032036" pp="4" l="9" ppth="Berlin Plänterwald|Berlin Treptower Park|Berlin Warschauer Straße|Berlin Ostbahnhof (S)|Berlin Jannowitzbrücke|Berlin Alexanderplatz (S)|Berlin Hackescher Markt|Berlin Friedrichstraße (S)|Berlin Hbf (S-Bahn)|Berlin Bellevue|Berlin-Tiergarten|Berlin Zoologischer Garten (S)|Berlin Savignyplatz|Berlin Charlottenburg (S)|Berlin Westkreuz|Berlin Messe Süd (Eichkamp)|Berlin Heerstraße|Berlin Olympiastadion|Berlin-Pichelsberg|Berlin-Stresow|Berlin-Spandau (S)" />
  </s>
  <s id="-5997330315550937134-2509032045-5">
    <tl f="S" t="p" o="08" c="S" n="8135" />
    <ar pt="2509032055" pp="3" l="8" ppth="Berlin Frankfurter Allee|Berlin Ostkreuz (S)|Berlin Treptower Park|Berlin Plänterwald" />
    <dp pt="2509032055" pp="3" l="8" ppth="Berlin-Schöneweide (S)|Berlin-Johannisthal|Berlin-Adlershof|Berlin-Grünau" />
  </s>
  <s id="-5092172834916827899-2509032028-2">
    <tl f="S" t="p" o="08" c="S" n="85602" />
    <ar pt="2509032030" pp="4" l="85" ppth="Berlin-Schöneweide (S)" />
    <dp pt="2509032030" pp="4" l="85" ppth="Berlin Plänterwald|Berlin Treptower Park|Berlin Ostkreuz (S)|Berlin Frankfurter Allee" />
  </s>
  <s id="528012096107723141-2509032009-4">
    <tl f="S" t="p" o="08" c="S" n="47148" />
    <ar pt="2509032018" pp="4" l="47" ppth="Berlin-Spindlersfeld|Berlin-Oberspree|Berlin-Schöneweide (S)" />
    <dp pt="2509032018" pp="4" l="47" ppth="Berlin Köllnische Heide|Berlin-Neukölln|Berlin Hermannstraße" />
  </s>
  <s id="3377647720781430757-2509031949-9">
    <tl f="S" t="p" o="08" c="S" n="9126" />
    <ar pt="2509032015" pp="4" l="9" ppth="Flughafen BER (S-Bahn)|Waßmannsdorf|Schönefeld(bei Berlin)|Berlin Grünbergallee|Berlin-Altglienicke|Berlin-Adlershof|Berlin-Johannisthal|Berlin-Schöneweide (S)" />
    <dp pt="2509032016" pp="4" l="9" ppth="Berlin Plänterwald|Berlin Treptower Park|Berlin Warschauer Straße|Berlin Ostbahnhof (S)|Berlin Jannowitzbrücke|Berlin Alexanderplatz (S)|Berlin Hackescher Markt|Berlin Friedrichstraße (S)|Berlin Hbf (S-Bahn)|Berlin Bellevue|Berlin-Tiergarten|Berlin Zoologischer Garten (S)|Berlin Savignyplatz|Berlin Charlottenburg (S)|Berlin Westkreuz|Berlin Messe Süd (Eichkamp)|Berlin Heerstraße|Berlin Olympiastadion|Berlin-Pichelsberg|Berlin-Stresow|Berlin-Spandau (S)" />
  </s>
  <s id="-7009186681311784332-2509032029-4">
    <tl f="S" t="p" o="08" c="S" n="47150" />
    <ar pt="2509032038" pp="4" l="47" ppth="Berlin-Spindlersfeld|Berlin-Oberspree|Berlin-Schöneweide (S)" />
    <dp pt="2509032038" pp="4" l="47" ppth="Berlin Köllnische Heide|Berlin-Neukölln|Berlin Hermannstraße" />
  </s>
  <s id="-2809615097602398279-2509032015-5">
    <tl f="S" t="p" o="08" c="S" n="85601" />
    <ar pt="2509032025" pp="3" l="85" ppth="Berlin Frankfurter Allee|Berlin Ostkreuz (S)|Berlin Treptower Park|Berlin Plänterwald" />
    <dp pt="2509032025" pp="3" l="85" ppth="Berlin-Schöneweide (S)" />
  </s>
  <s id="8534211473671313284-2509031941-9">
    <tl f="S" t="p" o="08" c="S" n="46112" />
    <ar pt="2509032007" pp="4" l="46" ppth="Königs Wusterhausen|Wildau|Zeuthen|Eichwalde|Berlin-Grünau|Berlin-Adlershof|Berlin-Johannisthal|Berlin-Schöneweide (S)" />
    <dp pt="2509032008" pp="4" l="46" ppth="Berlin Köllnische Heide|Berlin-Neukölln|Berlin Hermannstraße|Berlin-Tempelhof|Berlin Südkreuz (S)|Berlin-Schöneberg|Berlin Innsbrucker Platz|Berlin Bundesplatz|Berlin Heidelberger Platz|Berlin Hohenzollerndamm|Berlin-Halensee|Berlin Westkreuz|Berlin Messe Nord/ZOB (Witzleben)|Berlin Westend" />
  </s>
  <s id="9094929484097139052-2509032024-4">
    <tl f="S" t="p" o="08" c="S" n="47151" />
    <ar pt="2509032031" pp="5" l="47" ppth="Berlin Hermannstraße|Berlin-Neukölln|Berlin Köllnische Heide" />
    <dp pt="2509032033" pp="5" l="47" ppth="Berlin-Schöneweide (S)|Berlin-Oberspree|Berlin-Spindlersfeld" />
  </s>
  <s id="3500788535558609352-2509031937-9">
    <tl f="S" t="p" o="08" c="S" n="45106" />
    <ar pt="2509032002" pp="4" l="45" ppth="Flughafen BER (S-Bahn)|Waßmannsdorf|Schönefeld(bei Berlin)|Berlin Grünbergallee|Berlin-Altglienicke|Berlin-Adlershof|Berlin-Johannisthal|Berlin-Schöneweide (S)" />
    <dp pt="2509032003" pp="4" l="45" ppth="Berlin Köllnische Heide|Berlin-Neukölln|Berlin Hermannstraße|Berlin-Tempelhof|Berlin Südkreuz (S)" />
  </s>
  <s id="5518611597516240812-2509031949-5">
    <tl f="S" t="p" o="08" c="S" n="8132" />
    <ar pt="2509032000" pp="4" l="8" ppth="Berlin-Grünau|Berlin-Adlershof|Berlin-Johannisthal|Berlin-Schöneweide (S)" />
    <dp pt="2509032000" pp="4" l="8" ppth="Berlin Plänterwald|Berlin Treptower Park|Berlin Ostkreuz (S)|Berlin Frankfurter Allee" />
  </s>
  <s id="2083850143317304381-2509031936-15">
    <tl f="S" t="p" o="08" c="S" n="46111" />
    <ar pt="2509032006" pp="5" l="46" ppth="Berlin Westend|Berlin Messe Nord/ZOB (Witzleben)|Berlin Westkreuz|Berlin-Halensee|Berlin Hohenzollerndamm|Berlin Heidelberger Platz|Berlin Bundesplatz|Berlin Innsbrucker Platz|Berlin-Schöneberg|Berlin Südkreuz (S)|Berlin-Tempelhof|Berlin Hermannstraße|Berlin-Neukölln|Berlin Köllnische Heide" />
    <dp pt="2509032008" pp="5" l="46" ppth="Berlin-Schöneweide (S)|Berlin-Johannisthal|Berlin-Adlershof|Berlin-Grünau|Eichwalde|Zeuthen|Wildau|Königs Wusterhausen" />
  </s>
  <s id="5144617548520349814-2509031957-22">
    <tl f="S" t="p" o="08" c="S" n="9127" />
    <ar pt="2509032047" pp="3" l="9" ppth="Berlin-Spandau (S)|Berlin-Stresow|Berlin-Pichelsberg|Berlin Olympiastadion|Berlin Heerstraße|Berlin Messe Süd (Eichkamp)|Berlin Westkreuz|Berlin Charlottenburg (S)|Berlin Savignyplatz|Berlin Zoologischer Garten (S)|Berlin-Tiergarten|Berlin Bellevue|Berlin Hbf (S-Bahn)|Berlin Friedrichstraße (S)|Berlin Hackescher Markt|Berlin Alexanderplatz (S)|Berlin Jannowitzbrücke|Berlin Ostbahnhof (S)|Berlin Warschauer Straße|Berlin Treptower Park|Berlin Plänterwald" />
    <dp pt="2509032050" pp="3" l="9" ppth="Berlin-Schöneweide (S)|Berlin-Johannisthal|Berlin-Adlershof|Berlin-Altglienicke|Berlin Grünbergallee|Schönefeld(bei Berlin)|Waßmannsdorf|Flughafen BER (S-Bahn)" />
  </s>
  <s id="-3059100573675703891-2509032004-4">
    <tl f="S" t="p" o="08" c="S" n="47149" />
    <ar pt="2509032011" pp="5" l="47" ppth="Berlin Hermannstraße|Berlin-Neukölln|Berlin Köllnische Heide" />
    <dp pt="2509032013" pp="5" l="47" ppth="Berlin-Schöneweide (S)|Berlin-Oberspree|Berlin-Spindlersfeld" />
  </s>
  <s id="-5783293943799575612-2509031917-22">
    <tl f="S" t="p" o="08" c="S" n="9423" />
    <ar pt="2509032007" pp="3" l="9" ppth="Berlin-Spandau (S)|Berlin-Stresow|Berlin-Pichelsberg|Berlin Olympiastadion|Berlin Heerstraße|Berlin Messe Süd (Eichkamp)|Berlin Westkreuz|Berlin Charlottenburg (S)|Berlin Savignyplatz|Berlin Zoologischer Garten (S)|Berlin-Tiergarten|Berlin Bellevue|Berlin Hbf (S-Bahn)|Berlin Friedrichstraße (S)|Berlin Hackescher Markt|Berlin Alexanderplatz (S)|Berlin Jannowitzbrücke|Berlin Ostbahnhof (S)|Berlin Warschauer Straße|Berlin Treptower Park|Berlin Plänterwald" />
    <dp pt="2509032010" pp="3" l="9" ppth="Berlin-Schöneweide (S)|Berlin-Johannisthal|Berlin-Adlershof|Berlin-Altglienicke|Berlin Grünbergallee|Schönefeld(bei Berlin)|Waßmannsdorf|Flughafen BER (S-Bahn)" />
  </s>
  <s id="8781851569575991948-2509032048-2">
    <tl f="S" t="p" o="08" c="S" n="85604" />
    <ar pt="2509032050" pp="4" l="85" ppth="Berlin-Schöneweide (S)" />
    <dp pt="2509032050" pp="4" l="85" ppth="Berlin Plänterwald|Berlin Treptower Park|Berlin Ostkreuz (S)|Berlin Frankfurter Allee" />
  </s>
  <s id="1361851905129153110-2509032015-20">
    <tl f="S" t="p" o="08" c="S" n="4275" />
    <ar pt="2509032057" pp="5" l="42" ppth="Berlin Gesundbrunnen(S)|Berlin-Wedding|Berlin Westhafen|Berlin Beusselstraße|Berlin Jungfernheide (S)|Berlin Westend|Berlin Messe Nord/ZOB (Witzleben)|Berlin Westkreuz|Berlin-Halensee|Berlin Hohenzollerndamm|Berlin Heidelberger Platz|Berlin Bundesplatz|Berlin Innsbrucker Platz|Berlin-Schöneberg|Berlin Südkreuz (S)|Berlin-Tempelhof|Berlin Hermannstraße|Berlin-Neukölln|Berlin Köllnische Heide" />
    <dp pt="2509032058" pp="5" l="42" ppth="Berlin-Schöneweide (S)|Berlin-Johannisthal|Berlin-Adlershof|Berlin-Grünau" />
  </s>
  <s id="-8927529160179240899-2509032009-5">
    <tl f="S" t="p" o="08" c="S" n="8134" />
    <ar pt="2509032020" pp="4" l="8" ppth="Berlin-Grünau|Berlin-Adlershof|Berlin-Johannisthal|Berlin-Schöneweide (S)" />
    <dp pt="2509032020" pp="4" l="8" ppth="Berlin Plänterwald|Berlin Treptower Park|Berlin Ostkreuz (S)|Berlin Frankfurter Allee" />
  </s>
  <s id="6223330266090977655-2509031948-6">
    <tl f="S" t="p" o="08" c="S" n="45109" />
    <ar pt="2509032000" pp="5" l="45" ppth="Berlin Südkreuz (S)|Berlin-Tempelhof|Berlin Hermannstraße|Berlin-Neukölln|Berlin Köllnische Heide" />
    <dp pt="2509032001" pp="5" l="45" ppth="Berlin-Schöneweide (S)|Berlin-Johannisthal|Berlin-Adlershof|Berlin-Altglienicke|Berlin Grünbergallee|Schönefeld(bei Berlin)|Waßmannsdorf|Flughafen BER (S-Bahn)" />
  </s>
  <s id="-5874207931311033574-2509032029-9">
    <tl f="S" t="p" o="08" c="S" n="9130" />
    <ar pt="2509032055" pp="4" l="9" ppth="Flughafen BER (S-Bahn)|Waßmannsdorf|Schönefeld(bei Berlin)|Berlin Grünbergallee|Berlin-Altglienicke|Berlin-Adlershof|Berlin-Johannisthal|Berlin-Schöneweide (S)" />
    <dp pt="2509032056" pp="4" l="9" ppth="Berlin Plänterwald|Berlin Treptower Park|Berlin Warschauer Straße|Berlin Ostbahnhof (S)|Berlin Jannowitzbrücke|Berlin Alexanderplatz (S)|Berlin Hackescher Markt|Berlin Friedrichstraße (S)|Berlin Hbf (S-Bahn)|Berlin Bellevue|Berlin-Tiergarten|Berlin Zoologischer Garten (S)|Berlin Savignyplatz|Berlin Charlottenburg (S)|Berlin Westkreuz|Berlin Messe Süd (Eichkamp)|Berlin Heerstraße|Berlin Olympiastadion|Berlin-Pichelsberg|Berlin-Stresow|Berlin-Spandau (S)" />
  </s>
  <s id="8970686012061115818-2509032017-9">
    <tl f="S" t="p" o="08" c="S" n="45110" />
    <ar pt="2509032042" pp="4" l="45" ppth="Flughafen BER (S-Bahn)|Waßmannsdorf|Schönefeld(bei Berlin)|Berlin Grünbergallee|Berlin-Altglienicke|Berlin-Adlershof|Berlin-Johannisthal|Berlin-Schöneweide (S)" />
    <dp pt="2509032043" pp="4" l="45" ppth="Berlin Köllnische Heide|Berlin-Neukölln|Berlin Hermannstraße|Berlin-Tempelhof|Berlin Südkreuz (S)" />
  </s>
  <s id="-4494971484852230663-2509032028-6">
    <tl f="S" t="p" o="08" c="S" n="45113" />
    <ar pt="2509032040" pp="5" l="45" ppth="Berlin Südkreuz (S)|Berlin-Tempelhof|Berlin Hermannstraße|Berlin-Neukölln|Berlin Köllnische Heide" />
    <dp pt="2509032041" pp="5" l="45" ppth="Berlin-Schöneweide (S)|Berlin-Johannisthal|Berlin-Adlershof|Berlin-Altglienicke|Berlin Grünbergallee|Schönefeld(bei Berlin)|Waßmannsdorf|Flughafen BER (S-Bahn)" />
  </s>
  <s id="8887403546845211459-2509032008-6">
    <tl f="S" t="p" o="08" c="S" n="45111" />
    <ar pt="2509032020" pp="5" l="45" ppth="Berlin Südkreuz (S)|Berlin-Tempelhof|Berlin Hermannstraße|Berlin-Neukölln|Berlin Köllnische Heide" />
    <dp pt="2509032021" pp="5" l="45" ppth="Berlin-Schöneweide (S)|Berlin-Johannisthal|Berlin-Adlershof|Berlin-Altglienicke|Berlin Grünbergallee|Schönefeld(bei Berlin)|Waßmannsdorf|Flughafen BER (S-Bahn)" />
  </s>
</timetable>