<?xml version='1.0' encoding='utf-8'?>
<timetable station="Berlin Alexanderplatz" eva="8011155">
  <s id="-7460128831778763104-2509050002-4" eva="8011155">
    <ar ct="2509050030" />
    <dp ct="2509050030" />
  </s>
  <s id="-4499169996640701986-2509050002-9" eva="8011155">
    <ar cpth="Wustermark|Elstal|Dallgow-Döberitz|Berlin-Staaken|Berlin-Spandau|Berlin Zoologischer Garten|Berlin Hbf|Berlin Friedrichstraße" ct="2509050047" l="8" />
    <dp cpth="Berlin Ostbahnhof" ct="2509050048" l="8" />
  </s>
</timetable>