<?xml version='1.0' encoding='utf-8'?>
<timetable station="Berlin Yorckstr.(S1)" eva="8089051">
  <s id="6195139372090621112-2509051811-22" eva="8089051">
    <ar ct="2509051908" l="1" />
    <dp ct="2509051908" l="1" />
  </s>
  <s id="-4842820653070917580-2509051834-14" eva="8089051">
    <ar ct="2509051900" l="1" />
    <dp ct="2509051901" l="1" />
  </s>
  <s id="-2294093891392781262-2509051915-17" eva="8089051">
    <ar ct="2509051954" l="1" />
    <dp ct="2509051955" l="1" />
  </s>
  <s id="7543069710296066844-2509051914-14" eva="8089051">
    <ar ct="2509051941" l="1" />
    <dp ct="2509051941" l="1" />
  </s>
</timetable>