<?xml version='1.0' encoding='utf-8'?>
<timetable station="Berlin Hbf" eva="8011160">
  <s id="5413975876871307459-2509081454-2" eva="8011160">
    <m id="r2488161" t="h" from="2509081015" to="2509082000" cat="Störung" ts="2509081045" ts-tts="25-09-08 19:16:04.557" pr="1" />
    <m id="r2415041" t="h" from="2505120800" to="2509202359" cat="Information" ts="2505112304" ts-tts="25-09-07 23:16:04.468" pr="3" />
    <ar ct="2509081502">
      <m id="r24338896" t="f" c="1000" ts="2509080215" ts-tts="25-09-08 02:15:57.779" />
      <m id="r24338899" t="f" c="0" ts="2509080215" ts-tts="25-09-08 02:15:57.779" />
      <m id="r24338900" t="f" c="0" ts="2509080215" ts-tts="25-09-08 02:15:57.779" />
      <m id="r24374087" t="f" c="0" ts="2509080938" ts-tts="25-09-08 09:38:59.963" />
      <m id="r24374149" t="f" c="0" ts="2509080939" ts-tts="25-09-08 09:39:31.227" />
    </ar>
    <dp ct="2509081506">
      <m id="r24338896" t="f" c="1000" ts="2509080215" ts-tts="25-09-08 02:15:57.779" />
      <m id="r24338899" t="f" c="0" ts="2509080215" ts-tts="25-09-08 02:15:57.779" />
      <m id="r24338900" t="f" c="0" ts="2509080215" ts-tts="25-09-08 02:15:57.779" />
      <m id="r24374087" t="f" c="0" ts="2509080938" ts-tts="25-09-08 09:38:59.963" />
      <m id="r24374149" t="f" c="0" ts="2509080939" ts-tts="25-09-08 09:39:31.227" />
    </dp>
  </s>
  <s id="-7732825863849667402-2509081132-2" eva="8011160">
    <m id="r2488161" t="h" from="2509081015" to="2509082000" cat="Störung" ts="2509081045" ts-tts="25-09-08 19:16:04.557" pr="1" />
    <m id="r2415041" t="h" from="2505120800" to="2509202359" cat="Information" ts="2505112304" ts-tts="25-09-07 23:16:04.468" pr="3" />
    <ar ct="2509081142" />
    <dp ct="2509081146">
      <m id="r24383990" t="f" c="0" ts="2509081047" ts-tts="25-09-08 10:47:08.772" />
      <m id="r24383991" t="f" c="0" ts="2509081047" ts-tts="25-09-08 10:47:08.772" />
      <m id="r24383992" t="f" c="0" ts="2509081047" ts-tts="25-09-08 10:47:08.772" />
      <m id="r24383993" t="f" c="0" ts="2509081047" ts-tts="25-09-08 10:47:08.772" />
      <m id="r24390615" t="f" c="0" ts="2509081130" ts-tts="25-09-08 11:30:10.887" />
      <m id="r24390617" t="f" c="0" ts="2509081130" ts-tts="25-09-08 11:30:10.887" />
      <m id="r24390616" t="f" c="0" ts="2509081130" ts-tts="25-09-08 11:30:10.887" />
      <m id="r24390618" t="f" c="0" ts="2509081130" ts-tts="25-09-08 11:30:10.887" />
      <m id="r24390619" t="f" c="0" ts="2509081130" ts-tts="25-09-08 11:30:10.887" />
      <m id="r24390620" t="f" c="0" ts="2509081130" ts-tts="25-09-08 11:30:10.887" />
      <m id="r24390621" t="f" c="0" ts="2509081130" ts-tts="25-09-08 11:30:10.887" />
      <m id="r24390623" t="f" c="0" ts="2509081130" ts-tts="25-09-08 11:30:10.887" />
      <m id="r24390622" t="f" c="0" ts="2509081130" ts-tts="25-09-08 11:30:10.887" />
      <m id="r24390626" t="f" c="0" ts="2509081130" ts-tts="25-09-08 11:30:10.887" />
      <m id="r24390628" t="f" c="0" ts="2509081130" ts-tts="25-09-08 11:30:10.887" />
      <m id="r24390627" t="f" c="0" ts="2509081130" ts-tts="25-09-08 11:30:10.887" />
    </dp>
  </s>
  <s id="5868363889496507967-2509081332-2" eva="8011160">
    <m id="r2488161" t="h" from="2509081015" to="2509082000" cat="Störung" ts="2509081045" ts-tts="25-09-08 19:16:04.557" pr="1" />
    <m id="r2415041" t="h" from="2505120800" to="2509202359" cat="Information" ts="2505112304" ts-tts="25-09-07 23:16:04.468" pr="3" />
    <m id="r2488056" t="h" from="2509080618" to="2509081841" cat="Information" ts="2509080849" ts-tts="25-09-08 08:50:07.010" pr="3" />
    <ar ct="2509081342">
      <m id="r24367268" t="q" c="98" ts="2509080850" ts-tts="25-09-08 08:50:54.396" />
      <m id="r24367271" t="q" c="98" ts="2509080850" ts-tts="25-09-08 08:50:54.396" />
      <m id="r24403830" t="f" c="0" ts="2509081251" ts-tts="25-09-08 12:51:13.501" />
    </ar>
    <dp ct="2509081346">
      <m id="r24367268" t="q" c="98" ts="2509080850" ts-tts="25-09-08 08:50:54.396" />
      <m id="r24367271" t="q" c="98" ts="2509080850" ts-tts="25-09-08 08:50:54.396" />
      <m id="r24403830" t="f" c="0" ts="2509081251" ts-tts="25-09-08 12:51:13.501" />
      <m id="r24409235" t="f" c="0" ts="2509081322" ts-tts="25-09-08 13:22:52.404" />
      <m id="r24409237" t="f" c="0" ts="2509081322" ts-tts="25-09-08 13:22:52.404" />
      <m id="r24409236" t="f" c="0" ts="2509081322" ts-tts="25-09-08 13:22:52.404" />
      <m id="r24409239" t="f" c="0" ts="2509081322" ts-tts="25-09-08 13:22:52.404" />
      <m id="r24409241" t="f" c="0" ts="2509081322" ts-tts="25-09-08 13:22:52.404" />
      <m id="r24409240" t="f" c="0" ts="2509081322" ts-tts="25-09-08 13:22:52.404" />
      <m id="r24409249" t="f" c="0" ts="2509081322" ts-tts="25-09-08 13:22:52.404" />
      <m id="r24409251" t="f" c="0" ts="2509081322" ts-tts="25-09-08 13:22:52.404" />
      <m id="r24409250" t="f" c="0" ts="2509081322" ts-tts="25-09-08 13:22:52.404" />
      <m id="r24409752" t="f" c="0" ts="2509081325" ts-tts="25-09-08 13:25:14.460" />
    </dp>
  </s>
  <s id="-6123363187143113361-2509081033-2" eva="8011160">
    <m id="r2488161" t="h" from="2509081015" to="2509082000" cat="Störung" ts="2509081045" ts-tts="25-09-08 19:16:04.557" pr="1" />
    <m id="r2415041" t="h" from="2505120800" to="2509202359" cat="Information" ts="2505112304" ts-tts="25-09-07 23:16:04.468" pr="3" />
    <m id="r2487909" t="h" from="2509081033" to="2509082128" cat="Information" ts="2509080257" ts-tts="25-09-08 02:57:41.536" pr="2" />
    <ar cp="13" ct="2509081046">
      <m id="r24338746" t="f" c="0" ts="2509080206" ts-tts="25-09-08 02:06:02.174" />
      <m id="r24338759" t="f" c="0" ts="2509080206" ts-tts="25-09-08 02:07:03.303" />
      <m id="r24338772" t="f" c="1000" ts="2509080207" ts-tts="25-09-08 02:07:18.613" />
      <m id="r24338774" t="f" c="0" ts="2509080207" ts-tts="25-09-08 02:07:33.893" />
      <m id="r24338780" t="q" c="92" ts="2509080207" ts-tts="25-09-08 02:08:04.411" />
      <m id="r24338782" t="q" c="92" ts="2509080207" ts-tts="25-09-08 02:08:04.411" />
    </ar>
    <dp cp="13" ct="2509081049">
      <m id="r24338746" t="f" c="0" ts="2509080206" ts-tts="25-09-08 02:06:02.174" />
      <m id="r24338759" t="f" c="0" ts="2509080206" ts-tts="25-09-08 02:07:03.303" />
      <m id="r24338772" t="f" c="1000" ts="2509080207" ts-tts="25-09-08 02:07:18.613" />
      <m id="r24338774" t="f" c="0" ts="2509080207" ts-tts="25-09-08 02:07:33.893" />
      <m id="r24338780" t="q" c="92" ts="2509080207" ts-tts="25-09-08 02:08:04.411" />
      <m id="r24338782" t="q" c="92" ts="2509080207" ts-tts="25-09-08 02:08:04.411" />
      <m id="r24372505" t="f" c="0" ts="2509080927" ts-tts="25-09-08 09:27:14.198" />
      <m id="r24372508" t="f" c="0" ts="2509080927" ts-tts="25-09-08 09:27:14.198" />
      <m id="r24372507" t="f" c="0" ts="2509080927" ts-tts="25-09-08 09:27:14.198" />
      <m id="r24372506" t="f" c="0" ts="2509080927" ts-tts="25-09-08 09:27:14.198" />
      <m id="r24372509" t="f" c="0" ts="2509080927" ts-tts="25-09-08 09:27:14.198" />
      <m id="r24372510" t="f" c="0" ts="2509080927" ts-tts="25-09-08 09:27:14.198" />
      <m id="r24372511" t="f" c="0" ts="2509080927" ts-tts="25-09-08 09:27:14.198" />
      <m id="r24372512" t="f" c="0" ts="2509080927" ts-tts="25-09-08 09:27:14.198" />
      <m id="r24372513" t="f" c="0" ts="2509080927" ts-tts="25-09-08 09:27:14.198" />
      <m id="r24372516" t="f" c="0" ts="2509080927" ts-tts="25-09-08 09:27:14.198" />
      <m id="r24372515" t="f" c="0" ts="2509080927" ts-tts="25-09-08 09:27:14.198" />
      <m id="r24372514" t="f" c="0" ts="2509080927" ts-tts="25-09-08 09:27:14.198" />
    </dp>
  </s>
  <s id="1677073591470788837-2509081232-2" eva="8011160">
    <m id="r2488161" t="h" from="2509081015" to="2509082000" cat="Störung" ts="2509081045" ts-tts="25-09-08 19:16:04.557" pr="1" />
    <m id="r2415041" t="h" from="2505120800" to="2509202359" cat="Information" ts="2505112304" ts-tts="25-09-07 23:16:04.468" pr="3" />
    <m id="r2455835" t="h" from="2507100729" to="2512132359" cat="Information" ts="2507100734" ts-tts="25-09-07 23:16:04.482" pr="2" />
    <ar ct="2509081242" />
    <dp ct="2509081247" />
  </s>
  <s id="-7486736309392519814-2509081432-2" eva="8011160">
    <m id="r2488161" t="h" from="2509081015" to="2509082000" cat="Störung" ts="2509081045" ts-tts="25-09-08 19:16:04.557" pr="1" />
    <m id="r2415041" t="h" from="2505120800" to="2509202359" cat="Information" ts="2505112304" ts-tts="25-09-07 23:16:04.468" pr="3" />
    <m id="r2388354" t="h" from="2412150000" to="2512132359" cat="Information" ts="2504111440" ts-tts="25-09-07 23:16:04.465" pr="2" />
    <ar ct="2509081443" />
    <dp ct="2509081448">
      <m id="r24409234" t="f" c="0" ts="2509081322" ts-tts="25-09-08 13:22:36.548" />
    </dp>
  </s>
  <s id="1341469202977470214-2509080932-2" eva="8011160">
    <m id="r2488161" t="h" from="2509081015" to="2509082000" cat="Störung" ts="2509081045" ts-tts="25-09-08 19:16:04.557" pr="1" />
    <m id="r2415041" t="h" from="2505120800" to="2509202359" cat="Information" ts="2505112304" ts-tts="25-09-07 23:16:04.468" pr="3" />
    <ar ct="2509080941" />
    <dp ct="2509080946">
      <m id="r24372409" t="f" c="0" ts="2509080926" ts-tts="25-09-08 09:26:58.572" />
      <m id="r24372410" t="f" c="0" ts="2509080926" ts-tts="25-09-08 09:26:58.572" />
      <m id="r24372411" t="f" c="0" ts="2509080926" ts-tts="25-09-08 09:26:58.572" />
      <m id="r24372412" t="f" c="0" ts="2509080926" ts-tts="25-09-08 09:26:58.572" />
      <m id="r24372517" t="f" c="0" ts="2509080927" ts-tts="25-09-08 09:27:14.198" />
      <m id="r24372518" t="f" c="0" ts="2509080927" ts-tts="25-09-08 09:27:14.198" />
    </dp>
  </s>
  <s id="5703989328735164692-2509080932-2" eva="8011160">
    <m id="r2488161" t="h" from="2509081015" to="2509082000" cat="Störung" ts="2509081045" ts-tts="25-09-08 19:16:04.557" pr="1" />
    <m id="r2415041" t="h" from="2505120800" to="2509202359" cat="Information" ts="2505112304" ts-tts="25-09-07 23:16:04.468" pr="3" />
    <m id="r2488125" t="h" from="2509080932" to="2509082028" cat="Information" ts="2509080959" ts-tts="25-09-08 09:59:44.051" pr="2" />
    <ar ct="2509080940" />
    <dp ct="2509080946">
      <m id="r24372405" t="f" c="0" ts="2509080926" ts-tts="25-09-08 09:26:58.572" />
      <m id="r24372406" t="f" c="0" ts="2509080926" ts-tts="25-09-08 09:26:58.572" />
      <m id="r24372407" t="f" c="0" ts="2509080926" ts-tts="25-09-08 09:26:58.572" />
      <m id="r24372408" t="f" c="0" ts="2509080926" ts-tts="25-09-08 09:26:58.572" />
      <m id="r24372497" t="f" c="0" ts="2509080927" ts-tts="25-09-08 09:27:14.198" />
    </dp>
  </s>
  <s id="563323919548594377-2509080832-2" eva="8011160">
    <m id="r2488161" t="h" from="2509081015" to="2509082000" cat="Störung" ts="2509081045" ts-tts="25-09-08 19:16:04.557" pr="1" />
    <m id="r2415041" t="h" from="2505120800" to="2509202359" cat="Information" ts="2505112304" ts-tts="25-09-07 23:16:04.468" pr="3" />
    <m id="r2487908" t="h" from="2509080349" to="2509081927" cat="Information" ts="2509080253" ts-tts="25-09-08 02:53:37.310" pr="3" />
    <ar ct="2509080842">
      <m id="r24338734" t="f" c="0" ts="2509080204" ts-tts="25-09-08 02:05:00.993" />
      <m id="r24338738" t="f" c="1000" ts="2509080205" ts-tts="25-09-08 02:05:31.617" />
      <m id="r24338739" t="f" c="0" ts="2509080205" ts-tts="25-09-08 02:05:31.617" />
      <m id="r24338740" t="f" c="0" ts="2509080205" ts-tts="25-09-08 02:05:31.617" />
      <m id="r24339811" t="q" c="98" ts="2509080251" ts-tts="25-09-08 02:51:20.057" />
      <m id="r24339813" t="q" c="98" ts="2509080251" ts-tts="25-09-08 02:51:20.057" />
    </ar>
    <dp ct="2509080846">
      <m id="r24338734" t="f" c="0" ts="2509080204" ts-tts="25-09-08 02:05:00.993" />
      <m id="r24338738" t="f" c="1000" ts="2509080205" ts-tts="25-09-08 02:05:31.617" />
      <m id="r24338739" t="f" c="0" ts="2509080205" ts-tts="25-09-08 02:05:31.617" />
      <m id="r24338740" t="f" c="0" ts="2509080205" ts-tts="25-09-08 02:05:31.617" />
      <m id="r24339811" t="q" c="98" ts="2509080251" ts-tts="25-09-08 02:51:20.057" />
      <m id="r24339813" t="q" c="98" ts="2509080251" ts-tts="25-09-08 02:51:20.057" />
    </dp>
  </s>
  <s id="-5526084993451463045-2509080732-2" eva="8011160">
    <m id="r2488161" t="h" from="2509081015" to="2509082000" cat="Störung" ts="2509081045" ts-tts="25-09-08 19:16:04.557" pr="1" />
    <m id="r2415041" t="h" from="2505120800" to="2509202359" cat="Information" ts="2505112304" ts-tts="25-09-07 23:16:04.468" pr="3" />
    <ar cpth="" cs="c" clt="2509080021">
      <m id="r24335210" t="f" c="0" ts="2509080020" ts-tts="25-09-08 00:20:12.968" />
      <m id="r24335257" t="d" c="37" ts="2509080021" ts-tts="25-09-08 00:21:45.190" />
      <m id="r24335259" t="d" c="37" ts="2509080021" ts-tts="25-09-08 00:21:45.190" />
    </ar>
    <dp cpth="" cs="c" clt="2509080021">
      <m id="r24335210" t="f" c="0" ts="2509080020" ts-tts="25-09-08 00:20:12.968" />
      <m id="r24335257" t="d" c="37" ts="2509080021" ts-tts="25-09-08 00:21:45.190" />
      <m id="r24335259" t="d" c="37" ts="2509080021" ts-tts="25-09-08 00:21:45.190" />
    </dp>
  </s>
  <s id="-6543090459025161898-2509080732-2" eva="8011160">
    <m id="r2488161" t="h" from="2509081015" to="2509082000" cat="Störung" ts="2509081045" ts-tts="25-09-08 19:16:04.557" pr="1" />
    <m id="r2415041" t="h" from="2505120800" to="2509202359" cat="Information" ts="2505112304" ts-tts="25-09-07 23:16:04.468" pr="3" />
    <m id="r2487903" t="h" from="2509080732" to="2509081049" cat="Information" ts="2509080019" ts-tts="25-09-08 00:19:42.135" pr="2" />
    <m id="r2487960" t="h" from="2509080746" to="2509080928" cat="Information" ts="2509080519" ts-tts="25-09-08 05:19:18.583" pr="1" />
    <m id="r2487962" t="h" from="2509080931" to="2509081112" cat="Information" ts="2509080521" ts-tts="25-09-08 05:21:06.889" pr="1" />
    <ar ct="2509080741">
      <m id="r24335209" t="f" c="0" ts="2509080020" ts-tts="25-09-08 00:20:12.968" />
      <m id="r24336462" t="f" c="1000" ts="2509080106" ts-tts="25-09-08 01:06:36.730" />
      <m id="r24336489" t="q" c="82" ts="2509080107" ts-tts="25-09-08 01:07:22.775" />
      <m id="r24336491" t="q" c="82" ts="2509080107" ts-tts="25-09-08 01:07:22.775" />
      <m id="r24336492" t="q" c="82" ts="2509080107" ts-tts="25-09-08 01:07:22.775" />
      <m id="r24336494" t="q" c="82" ts="2509080107" ts-tts="25-09-08 01:07:22.775" />
    </ar>
    <dp ct="2509080746">
      <m id="r24335209" t="f" c="0" ts="2509080020" ts-tts="25-09-08 00:20:12.968" />
      <m id="r24336462" t="f" c="1000" ts="2509080106" ts-tts="25-09-08 01:06:36.730" />
      <m id="r24336489" t="q" c="82" ts="2509080107" ts-tts="25-09-08 01:07:22.775" />
      <m id="r24336491" t="q" c="82" ts="2509080107" ts-tts="25-09-08 01:07:22.775" />
      <m id="r24336492" t="q" c="82" ts="2509080107" ts-tts="25-09-08 01:07:22.775" />
      <m id="r24336494" t="q" c="82" ts="2509080107" ts-tts="25-09-08 01:07:22.775" />
    </dp>
  </s>
  <s id="-5777610419921593424-2509081532-2" eva="8011160">
    <m id="r2488161" t="h" from="2509081015" to="2509082000" cat="Störung" ts="2509081045" ts-tts="25-09-08 19:16:04.557" pr="1" />
    <m id="r2415041" t="h" from="2505120800" to="2509202359" cat="Information" ts="2505112304" ts-tts="25-09-07 23:16:04.468" pr="3" />
    <ar cp="13" ct="2509081543" />
    <dp cp="13" ct="2509081548" />
  </s>
  <s id="-7443151309671820141-2509081532-2" eva="8011160">
    <m id="r2488161" t="h" from="2509081015" to="2509082000" cat="Störung" ts="2509081045" ts-tts="25-09-08 19:16:04.557" pr="1" />
    <m id="r2415041" t="h" from="2505120800" to="2509202359" cat="Information" ts="2505112304" ts-tts="25-09-07 23:16:04.468" pr="3" />
    <ar cp="13" ct="2509081543" />
    <dp cp="13" ct="2509081548">
      <m id="r24429835" t="f" c="0" ts="2509081529" ts-tts="25-09-08 15:29:11.104" />
    </dp>
  </s>
  <s id="8210477890964980741-2509081632-2" eva="8011160">
    <m id="r2488161" t="h" from="2509081015" to="2509082000" cat="Störung" ts="2509081045" ts-tts="25-09-08 19:16:04.557" pr="1" />
    <m id="r2415041" t="h" from="2505120800" to="2509202359" cat="Information" ts="2505112304" ts-tts="25-09-07 23:16:04.468" pr="3" />
    <m id="r2455789" t="h" from="2412150000" to="2512132359" cat="Information" ts="2507100624" ts-tts="25-09-07 23:16:04.482" pr="2" />
    <m id="r2488238" t="h" from="2509081632" to="2509082135" cat="Information" ts="2509081319" ts-tts="25-09-08 13:19:10.219" pr="2" />
    <ar ct="2509081643">
      <m id="r24408458" t="q" c="83" ts="2509081318" ts-tts="25-09-08 13:18:23.032" />
      <m id="r24408460" t="q" c="83" ts="2509081318" ts-tts="25-09-08 13:18:23.032" />
    </ar>
    <dp ct="2509081646">
      <m id="r24408458" t="q" c="83" ts="2509081318" ts-tts="25-09-08 13:18:23.032" />
      <m id="r24408460" t="q" c="83" ts="2509081318" ts-tts="25-09-08 13:18:23.032" />
      <m id="r24443173" t="f" c="0" ts="2509081637" ts-tts="25-09-08 16:37:33.744" />
    </dp>
  </s>
  <s id="-5225265888807154878-2509081248-11" eva="8011160">
    <m id="r2415041" t="h" from="2505120800" to="2509202359" cat="Information" ts="2505112304" ts-tts="25-09-07 23:16:04.468" pr="3" />
    <m id="r2488158" t="h" from="2509081015" to="2509082000" cat="Störung" ts="2509081042" ts-tts="25-09-08 19:16:04.557" pr="1" />
    <m id="r982445770" t="c" ts="2509081738" ts-tts="25-09-08 17:39:02.614" />
    <m id="r982445771" t="c" ts="2509081738" ts-tts="25-09-08 17:39:02.614" />
    <m id="r982446047" t="c" ts="2509081755" ts-tts="25-09-08 17:56:02.008" />
    <m id="r982446048" t="c" ts="2509081755" ts-tts="25-09-08 17:56:02.008" />
    <m id="r982445767" t="c" ts="2509081738" ts-tts="25-09-08 17:39:02.614" />
    <m id="r982445768" t="c" ts="2509081738" ts-tts="25-09-08 17:39:02.614" />
    <m id="r982445769" t="c" ts="2509081738" ts-tts="25-09-08 17:39:02.614" />
    <m id="r982445763" t="c" ts="2509081738" ts-tts="25-09-08 17:39:02.614" />
    <m id="r982446049" t="c" ts="2509081755" ts-tts="25-09-08 17:56:02.008" />
    <m id="r982445764" t="c" ts="2509081738" ts-tts="25-09-08 17:39:02.614" />
    <m id="r982445765" t="c" ts="2509081738" ts-tts="25-09-08 17:39:02.614" />
    <m id="r982445766" t="c" ts="2509081738" ts-tts="25-09-08 17:39:02.614" />
    <ar ppth="Düsseldorf Hbf|Düsseldorf Flughafen|Duisburg Hbf|Essen Hbf|Dortmund Hbf|Bielefeld Hbf|Minden(Westf)|Hannover Hbf|Wolfsburg Hbf|Berlin-Spandau" pp="12" ct="2509081906" pt="2509081718">
      <m id="r24407765" t="d" c="47" ts="2509081314" ts-tts="25-09-08 13:14:25.322" />
      <m id="r24407767" t="d" c="47" ts="2509081314" ts-tts="25-09-08 13:14:25.322" />
      <m id="r24417950" t="d" c="58" ts="2509081414" ts-tts="25-09-08 14:14:53.522" />
      <m id="r24417952" t="d" c="58" ts="2509081414" ts-tts="25-09-08 14:14:53.522" />
      <m id="r24418503" t="f" c="0" ts="2509081419" ts-tts="25-09-08 14:19:06.861" />
      <m id="r24418504" t="f" c="0" ts="2509081419" ts-tts="25-09-08 14:19:06.861" />
      <m id="r24444657" t="f" c="0" ts="2509081646" ts-tts="25-09-08 16:46:53.661" />
      <m id="r24444916" t="f" c="0" ts="2509081649" ts-tts="25-09-08 16:49:48.711" />
      <m id="r24444917" t="f" c="0" ts="2509081649" ts-tts="25-09-08 16:49:48.711" />
      <m id="r24450316" t="f" c="0" ts="2509081717" ts-tts="25-09-08 17:17:46.299" />
      <m id="r24450317" t="f" c="0" ts="2509081717" ts-tts="25-09-08 17:17:46.299" />
      <m id="r24453630" t="f" c="0" ts="2509081738" ts-tts="25-09-08 17:39:02.780" />
      <m id="r24453632" t="f" c="0" ts="2509081738" ts-tts="25-09-08 17:39:02.780" />
      <m id="r24453631" t="f" c="0" ts="2509081738" ts-tts="25-09-08 17:39:02.780" />
      <m id="r24453634" t="f" c="0" ts="2509081738" ts-tts="25-09-08 17:39:02.780" />
      <m id="r24453636" t="f" c="0" ts="2509081738" ts-tts="25-09-08 17:39:02.780" />
      <m id="r24453635" t="f" c="0" ts="2509081738" ts-tts="25-09-08 17:39:02.780" />
      <m id="r24453980" t="f" c="0" ts="2509081741" ts-tts="25-09-08 17:41:57.805" />
      <m id="r24456183" t="f" c="0" ts="2509081754" ts-tts="25-09-08 17:54:10.289" />
      <m id="r24457963" t="f" c="0" ts="2509081807" ts-tts="25-09-08 18:07:43.940" />
    </ar>
    <dp ppth="Berlin Ostbahnhof" pp="12" ct="2509081909" pt="2509081721" hi="1">
      <m id="r24407765" t="d" c="47" ts="2509081314" ts-tts="25-09-08 13:14:25.322" />
      <m id="r24407767" t="d" c="47" ts="2509081314" ts-tts="25-09-08 13:14:25.322" />
      <m id="r24417950" t="d" c="58" ts="2509081414" ts-tts="25-09-08 14:14:53.522" />
      <m id="r24417952" t="d" c="58" ts="2509081414" ts-tts="25-09-08 14:14:53.522" />
      <m id="r24418503" t="f" c="0" ts="2509081419" ts-tts="25-09-08 14:19:06.861" />
      <m id="r24418504" t="f" c="0" ts="2509081419" ts-tts="25-09-08 14:19:06.861" />
      <m id="r24444657" t="f" c="0" ts="2509081646" ts-tts="25-09-08 16:46:53.661" />
      <m id="r24444916" t="f" c="0" ts="2509081649" ts-tts="25-09-08 16:49:48.711" />
      <m id="r24444917" t="f" c="0" ts="2509081649" ts-tts="25-09-08 16:49:48.711" />
      <m id="r24450316" t="f" c="0" ts="2509081717" ts-tts="25-09-08 17:17:46.299" />
      <m id="r24450317" t="f" c="0" ts="2509081717" ts-tts="25-09-08 17:17:46.299" />
      <m id="r24453980" t="f" c="0" ts="2509081741" ts-tts="25-09-08 17:41:57.805" />
      <m id="r24456183" t="f" c="0" ts="2509081754" ts-tts="25-09-08 17:54:10.289" />
      <m id="r24457963" t="f" c="0" ts="2509081807" ts-tts="25-09-08 18:07:43.940" />
    </dp>
    <tl f="F" t="p" o="80" c="ICE" n="549" />
  </s>
  <s id="-3272021131219238243-2509081749-4" eva="8011160">
    <m id="r2488158" t="h" from="2509081015" to="2509082000" cat="Störung" ts="2509081042" ts-tts="25-09-08 19:16:04.557" pr="1" />
    <ar ct="2509082234">
      <m id="r24455744" t="d" c="43" ts="2509081752" ts-tts="25-09-08 17:52:18.772" />
      <m id="r24455746" t="d" c="43" ts="2509081752" ts-tts="25-09-08 17:52:18.772" />
      <m id="r24456792" t="f" c="0" ts="2509081757" ts-tts="25-09-08 17:57:21.972" />
      <m id="r24456793" t="f" c="0" ts="2509081757" ts-tts="25-09-08 17:57:21.972" />
      <m id="r24456794" t="f" c="0" ts="2509081757" ts-tts="25-09-08 17:57:21.972" />
    </ar>
    <dp ct="2509082237">
      <m id="r24455744" t="d" c="43" ts="2509081752" ts-tts="25-09-08 17:52:18.772" />
      <m id="r24455746" t="d" c="43" ts="2509081752" ts-tts="25-09-08 17:52:18.772" />
      <m id="r24456792" t="f" c="0" ts="2509081757" ts-tts="25-09-08 17:57:21.972" />
      <m id="r24456793" t="f" c="0" ts="2509081757" ts-tts="25-09-08 17:57:21.972" />
      <m id="r24456794" t="f" c="0" ts="2509081757" ts-tts="25-09-08 17:57:21.972" />
    </dp>
  </s>
  <s id="-3876277476123700807-2509081247-13" eva="8011160">
    <m id="r2488158" t="h" from="2509081015" to="2509082000" cat="Störung" ts="2509081042" ts-tts="25-09-08 19:16:04.557" pr="1" />
    <m id="r982446740" t="c" ts="2509081850" ts-tts="25-09-08 18:50:11.480" />
    <m id="r982446742" t="c" ts="2509081850" ts-tts="25-09-08 18:50:11.480" />
    <ar ct="2509081912">
      <m id="r24389832" t="f" c="0" ts="2509081124" ts-tts="25-09-08 11:24:24.744" />
      <m id="r24389834" t="f" c="0" ts="2509081124" ts-tts="25-09-08 11:24:24.744" />
      <m id="r24400287" t="d" c="51" ts="2509081225" ts-tts="25-09-08 12:25:26.925" />
      <m id="r24400289" t="d" c="51" ts="2509081225" ts-tts="25-09-08 12:25:26.925" />
      <m id="r24426447" t="f" c="0" ts="2509081512" ts-tts="25-09-08 15:12:13.647" />
      <m id="r24431415" t="f" c="0" ts="2509081537" ts-tts="25-09-08 15:37:55.914" />
      <m id="r24431416" t="f" c="0" ts="2509081537" ts-tts="25-09-08 15:37:55.914" />
      <m id="r24459041" t="f" c="0" ts="2509081814" ts-tts="25-09-08 18:14:38.997" />
      <m id="r24459042" t="f" c="0" ts="2509081814" ts-tts="25-09-08 18:14:38.997" />
    </ar>
    <dp ct="2509081915">
      <m id="r24389832" t="f" c="0" ts="2509081124" ts-tts="25-09-08 11:24:24.744" />
      <m id="r24389834" t="f" c="0" ts="2509081124" ts-tts="25-09-08 11:24:24.744" />
      <m id="r24400287" t="d" c="51" ts="2509081225" ts-tts="25-09-08 12:25:26.925" />
      <m id="r24400289" t="d" c="51" ts="2509081225" ts-tts="25-09-08 12:25:26.925" />
      <m id="r24426447" t="f" c="0" ts="2509081512" ts-tts="25-09-08 15:12:13.647" />
      <m id="r24431415" t="f" c="0" ts="2509081537" ts-tts="25-09-08 15:37:55.914" />
      <m id="r24431416" t="f" c="0" ts="2509081537" ts-tts="25-09-08 15:37:55.914" />
      <m id="r24459041" t="f" c="0" ts="2509081814" ts-tts="25-09-08 18:14:38.997" />
      <m id="r24459042" t="f" c="0" ts="2509081814" ts-tts="25-09-08 18:14:38.997" />
    </dp>
  </s>
  <s id="211585818996437737-2509081050-10" eva="8011160">
    <m id="r2415041" t="h" from="2505120800" to="2509202359" cat="Information" ts="2505112304" ts-tts="25-09-07 23:16:04.467" pr="3" />
    <m id="r2488158" t="h" from="2509081015" to="2509082000" cat="Störung" ts="2509081042" ts-tts="25-09-08 19:16:04.557" pr="1" />
    <m id="r2487940" t="h" from="2509080411" to="2509082244" cat="Information" ts="2509080408" ts-tts="25-09-08 04:08:48.092" pr="2" />
    <m id="r982443870" t="c" ts="2509081531" ts-tts="25-09-08 15:31:18.182" />
    <m id="r982443874alt" t="c" ts="2509081531" ts-tts="25-09-08 15:31:18.327" />
    <m id="r982443904" t="c" ts="2509081533" ts-tts="25-09-08 15:33:40.658" />
    <m id="r982443903" t="c" ts="2509081533" ts-tts="25-09-08 15:33:40.658" />
    <m id="r982443902" t="c" ts="2509081533" ts-tts="25-09-08 15:33:40.658" />
    <m id="r982443901" t="c" ts="2509081533" ts-tts="25-09-08 15:33:40.658" />
    <m id="r982443908" t="c" ts="2509081533" ts-tts="25-09-08 15:34:12.461" />
    <m id="r982443907" t="c" ts="2509081533" ts-tts="25-09-08 15:34:12.461" />
    <m id="r982443903alt" t="c" ts="2509081533" ts-tts="25-09-08 15:33:40.814" />
    <m id="r982443874" t="c" ts="2509081531" ts-tts="25-09-08 15:31:18.182" />
    <m id="r982443871" t="c" ts="2509081531" ts-tts="25-09-08 15:31:18.182" />
    <m id="r982443900" t="c" ts="2509081533" ts-tts="25-09-08 15:33:40.658" />
    <m id="r982443899" t="c" ts="2509081533" ts-tts="25-09-08 15:33:40.658" />
    <m id="r982443898" t="c" ts="2509081533" ts-tts="25-09-08 15:33:40.658" />
    <m id="r982443875" t="c" ts="2509081531" ts-tts="25-09-08 15:31:18.182" />
    <ar cpth="Düsseldorf Hbf|Duisburg Hbf|Essen Hbf|Dortmund Hbf|Hamm(Westf)Hbf|Bielefeld Hbf|Minden(Westf)|Hannover Hbf|Wolfsburg Hbf|Berlin-Spandau" ct="2509081544">
      <m id="r24341596" t="q" c="83" ts="2509080407" ts-tts="25-09-08 04:08:02.252" />
      <m id="r24356043" t="f" c="0" ts="2509080724" ts-tts="25-09-08 07:24:23.750" />
      <m id="r24383064" t="d" c="57" ts="2509081040" ts-tts="25-09-08 10:40:51.572" />
      <m id="r24383066" t="d" c="57" ts="2509081040" ts-tts="25-09-08 10:40:51.572" />
      <m id="r24383164" t="f" c="0" ts="2509081041" ts-tts="25-09-08 10:41:23.019" />
      <m id="r24383165" t="f" c="0" ts="2509081041" ts-tts="25-09-08 10:41:23.019" />
      <m id="r24394703" t="d" c="64" ts="2509081150" ts-tts="25-09-08 11:50:40.353" />
      <m id="r24394705" t="d" c="64" ts="2509081150" ts-tts="25-09-08 11:50:40.353" />
      <m id="r24394706" t="d" c="64" ts="2509081150" ts-tts="25-09-08 11:50:40.353" />
      <m id="r24394708" t="d" c="64" ts="2509081150" ts-tts="25-09-08 11:50:40.353" />
      <m id="r24394709" t="d" c="64" ts="2509081150" ts-tts="25-09-08 11:50:40.353" />
      <m id="r24394711" t="d" c="64" ts="2509081150" ts-tts="25-09-08 11:50:40.353" />
      <m id="r24430338" t="f" c="0" ts="2509081531" ts-tts="25-09-08 15:32:05.951" />
      <m id="r24430648" t="f" c="0" ts="2509081533" ts-tts="25-09-08 15:33:40.785" />
      <m id="r24430649" t="f" c="0" ts="2509081533" ts-tts="25-09-08 15:33:40.785" />
      <m id="r24430650" t="f" c="0" ts="2509081533" ts-tts="25-09-08 15:33:40.785" />
      <m id="r24430651" t="f" c="0" ts="2509081533" ts-tts="25-09-08 15:33:40.785" />
    </ar>
    <dp cpth="Berlin Ostbahnhof" ct="2509081547">
      <m id="r24341596" t="q" c="83" ts="2509080407" ts-tts="25-09-08 04:08:02.252" />
      <m id="r24356043" t="f" c="0" ts="2509080724" ts-tts="25-09-08 07:24:23.750" />
      <m id="r24383064" t="d" c="57" ts="2509081040" ts-tts="25-09-08 10:40:51.572" />
      <m id="r24383066" t="d" c="57" ts="2509081040" ts-tts="25-09-08 10:40:51.572" />
      <m id="r24383164" t="f" c="0" ts="2509081041" ts-tts="25-09-08 10:41:23.019" />
      <m id="r24383165" t="f" c="0" ts="2509081041" ts-tts="25-09-08 10:41:23.019" />
      <m id="r24394703" t="d" c="64" ts="2509081150" ts-tts="25-09-08 11:50:40.353" />
      <m id="r24394705" t="d" c="64" ts="2509081150" ts-tts="25-09-08 11:50:40.354" />
      <m id="r24394706" t="d" c="64" ts="2509081150" ts-tts="25-09-08 11:50:40.354" />
      <m id="r24394708" t="d" c="64" ts="2509081150" ts-tts="25-09-08 11:50:40.354" />
      <m id="r24394709" t="d" c="64" ts="2509081150" ts-tts="25-09-08 11:50:40.354" />
      <m id="r24394711" t="d" c="64" ts="2509081150" ts-tts="25-09-08 11:50:40.354" />
    </dp>
  </s>
  <s id="-4020550040361167307-2509081345-8" eva="8011160">
    <m id="r2415041" t="h" from="2505120800" to="2509202359" cat="Information" ts="2505112304" ts-tts="25-09-07 23:16:04.468" pr="3" />
    <m id="r2488158" t="h" from="2509081015" to="2509082000" cat="Störung" ts="2509081042" ts-tts="25-09-08 19:16:04.557" pr="1" />
    <m id="r982446397" t="c" ts="2509081822" ts-tts="25-09-08 18:22:05.475" />
    <m id="r982446464" t="c" ts="2509081828" ts-tts="25-09-08 18:28:12.630" />
    <m id="r982446400" t="c" ts="2509081822" ts-tts="25-09-08 18:22:21.496" />
    <m id="r982446393" t="c" ts="2509081822" ts-tts="25-09-08 18:22:05.475" />
    <m id="r982446395" t="c" ts="2509081822" ts-tts="25-09-08 18:22:05.475" />
    <ar ppth="Köln Hbf|Wuppertal Hbf|Hagen Hbf|Hamm(Westf)Hbf|Hannover Hbf|Wolfsburg Hbf|Berlin-Spandau" pp="12" ct="2509081856" pt="2509081818" wings="-1360629902197387952-2509081343">
      <m id="r24419562" t="d" c="2" ts="2509081426" ts-tts="25-09-08 14:27:01.828" />
      <m id="r24419564" t="d" c="2" ts="2509081426" ts-tts="25-09-08 14:27:01.828" />
      <m id="r24419566" t="d" c="2" ts="2509081426" ts-tts="25-09-08 14:27:01.828" />
      <m id="r24454446" t="d" c="55" ts="2509081744" ts-tts="25-09-08 17:44:21.430" />
      <m id="r24454448" t="d" c="55" ts="2509081744" ts-tts="25-09-08 17:44:21.430" />
      <m id="r24460259" t="f" c="0" ts="2509081822" ts-tts="25-09-08 18:22:21.662" />
    </ar>
    <dp ppth="Berlin Ostbahnhof" pp="12" ct="2509081900" pt="2509081821" hi="1" wings="-1360629902197387952-2509081343">
      <m id="r24419562" t="d" c="2" ts="2509081426" ts-tts="25-09-08 14:27:01.828" />
      <m id="r24419564" t="d" c="2" ts="2509081426" ts-tts="25-09-08 14:27:01.828" />
      <m id="r24419566" t="d" c="2" ts="2509081426" ts-tts="25-09-08 14:27:01.828" />
      <m id="r24454446" t="d" c="55" ts="2509081744" ts-tts="25-09-08 17:44:21.430" />
      <m id="r24454448" t="d" c="55" ts="2509081744" ts-tts="25-09-08 17:44:21.430" />
    </dp>
    <tl f="F" t="p" o="80" c="ICE" n="951" />
  </s>
  <s id="6378881227509878523-2509081550-9" eva="8011160">
    <m id="r2415041" t="h" from="2505120800" to="2509202359" cat="Information" ts="2505112304" ts-tts="25-09-07 23:16:04.468" pr="3" />
    <m id="r2488158" t="h" from="2509081015" to="2509082000" cat="Störung" ts="2509081042" ts-tts="25-09-08 19:16:04.557" pr="1" />
    <ar ct="2509082026">
      <m id="r24452790" t="d" c="43" ts="2509081733" ts-tts="25-09-08 17:33:28.119" />
    </ar>
    <dp ct="2509082030">
      <m id="r24452790" t="d" c="43" ts="2509081733" ts-tts="25-09-08 17:33:28.119" />
    </dp>
  </s>
  <s id="-1360629902197387952-2509081343-10" eva="8011160">
    <m id="r2415041" t="h" from="2505120800" to="2509202359" cat="Information" ts="2505112304" ts-tts="25-09-07 23:16:04.468" pr="3" />
    <m id="r2488158" t="h" from="2509081015" to="2509082000" cat="Störung" ts="2509081042" ts-tts="25-09-08 19:16:04.557" pr="1" />
    <m id="r982446399" t="c" ts="2509081822" ts-tts="25-09-08 18:22:21.496" />
    <m id="r982446465" t="c" ts="2509081828" ts-tts="25-09-08 18:28:12.630" />
    <m id="r982446394" t="c" ts="2509081822" ts-tts="25-09-08 18:22:05.475" />
    <m id="r982446396" t="c" ts="2509081822" ts-tts="25-09-08 18:22:05.475" />
    <m id="r982446392" t="c" ts="2509081822" ts-tts="25-09-08 18:22:05.475" />
    <ar ppth="Düsseldorf Hbf|Düsseldorf Flughafen|Duisburg Hbf|Essen Hbf|Dortmund Hbf|Hamm(Westf)Hbf|Hannover Hbf|Wolfsburg Hbf|Berlin-Spandau" pp="12" ct="2509081856" pt="2509081818">
      <m id="r24454455" t="d" c="55" ts="2509081744" ts-tts="25-09-08 17:44:21.428" />
      <m id="r24454457" t="d" c="55" ts="2509081744" ts-tts="25-09-08 17:44:21.428" />
      <m id="r24454459" t="d" c="55" ts="2509081744" ts-tts="25-09-08 17:44:21.428" />
      <m id="r24460260" t="f" c="0" ts="2509081822" ts-tts="25-09-08 18:22:21.660" />
    </ar>
    <dp ppth="Berlin Ostbahnhof" pp="12" ct="2509081900" pt="2509081821" hi="1">
      <m id="r24454455" t="d" c="55" ts="2509081744" ts-tts="25-09-08 17:44:21.428" />
      <m id="r24454457" t="d" c="55" ts="2509081744" ts-tts="25-09-08 17:44:21.428" />
      <m id="r24454459" t="d" c="55" ts="2509081744" ts-tts="25-09-08 17:44:21.428" />
    </dp>
    <tl f="F" t="p" o="80" c="ICE" n="941" />
  </s>
  <s id="-9221432942161771616-2509081145-8" eva="8011160">
    <m id="r2415041" t="h" from="2505120800" to="2509202359" cat="Information" ts="2505112304" ts-tts="25-09-07 23:16:04.468" pr="3" />
    <m id="r2488158" t="h" from="2509081015" to="2509082000" cat="Störung" ts="2509081042" ts-tts="25-09-08 19:16:04.557" pr="1" />
    <m id="r982444308" t="c" ts="2509081602" ts-tts="25-09-08 16:02:22.507" />
    <m id="r982444310" t="c" ts="2509081602" ts-tts="25-09-08 16:02:22.507" />
    <m id="r982444309alt" t="c" ts="2509081602" ts-tts="25-09-08 16:02:22.648" />
    <m id="r982444310alt" t="c" ts="2509081602" ts-tts="25-09-08 16:02:22.648" />
    <m id="r982444314" t="c" ts="2509081602" ts-tts="25-09-08 16:02:22.507" />
    <m id="r982444797" t="c" ts="2509081638" ts-tts="25-09-08 16:38:05.406" />
    <m id="r982444312" t="c" ts="2509081602" ts-tts="25-09-08 16:02:22.507" />
    <m id="r982444306" t="c" ts="2509081602" ts-tts="25-09-08 16:02:22.507" />
    <ar ppth="Köln Hbf|Wuppertal Hbf|Hagen Hbf|Hamm(Westf)Hbf|Hannover Hbf|Wolfsburg Hbf|Berlin-Spandau" pp="12" ct="2509081656" pt="2509081618" wings="-3935110464616838577-2509081145">
      <m id="r24402092" t="d" c="31" ts="2509081238" ts-tts="25-09-08 12:38:35.550" />
      <m id="r24402094" t="d" c="31" ts="2509081238" ts-tts="25-09-08 12:38:35.550" />
      <m id="r24402096" t="d" c="31" ts="2509081238" ts-tts="25-09-08 12:38:35.550" />
      <m id="r24436879" t="f" c="0" ts="2509081602" ts-tts="25-09-08 16:02:38.583" />
      <m id="r24436880" t="f" c="0" ts="2509081602" ts-tts="25-09-08 16:02:38.583" />
      <m id="r24436883" t="f" c="0" ts="2509081602" ts-tts="25-09-08 16:02:38.583" />
      <m id="r24436884" t="f" c="0" ts="2509081602" ts-tts="25-09-08 16:02:38.583" />
      <m id="r24437048" t="d" c="36" ts="2509081603" ts-tts="25-09-08 16:03:26.423" />
    </ar>
    <dp ppth="Berlin Ostbahnhof" pp="12" ct="2509081659" pt="2509081621" hi="1" wings="-3935110464616838577-2509081145">
      <m id="r24402092" t="d" c="31" ts="2509081238" ts-tts="25-09-08 12:38:35.550" />
      <m id="r24402094" t="d" c="31" ts="2509081238" ts-tts="25-09-08 12:38:35.550" />
      <m id="r24402096" t="d" c="31" ts="2509081238" ts-tts="25-09-08 12:38:35.550" />
      <m id="r24437048" t="d" c="36" ts="2509081603" ts-tts="25-09-08 16:03:26.423" />
    </dp>
    <tl f="F" t="p" o="80" c="ICE" n="859" />
  </s>
  <s id="-3935110464616838577-2509081145-9" eva="8011160">
    <m id="r2415041" t="h" from="2505120800" to="2509202359" cat="Information" ts="2505112304" ts-tts="25-09-07 23:16:04.468" pr="3" />
    <m id="r2488158" t="h" from="2509081015" to="2509082000" cat="Störung" ts="2509081042" ts-tts="25-09-08 19:16:04.557" pr="1" />
    <m id="r982444309" t="c" ts="2509081602" ts-tts="25-09-08 16:02:22.507" />
    <m id="r982444309alt" t="c" ts="2509081602" ts-tts="25-09-08 16:02:22.648" />
    <m id="r982444310alt" t="c" ts="2509081602" ts-tts="25-09-08 16:02:22.648" />
    <m id="r982444313" t="c" ts="2509081602" ts-tts="25-09-08 16:02:22.507" />
    <m id="r982444796" t="c" ts="2509081638" ts-tts="25-09-08 16:38:05.406" />
    <m id="r982444311" t="c" ts="2509081602" ts-tts="25-09-08 16:02:22.507" />
    <m id="r982444307" t="c" ts="2509081602" ts-tts="25-09-08 16:02:22.507" />
    <m id="r982444305" t="c" ts="2509081602" ts-tts="25-09-08 16:02:22.507" />
    <ar ppth="Düsseldorf Hbf|Duisburg Hbf|Essen Hbf|Dortmund Hbf|Hamm(Westf)Hbf|Hannover Hbf|Wolfsburg Hbf|Berlin-Spandau" pp="12" ct="2509081656" pt="2509081618">
      <m id="r24341989" t="q" c="90" ts="2509080418" ts-tts="25-09-08 04:18:45.996" />
      <m id="r24341991" t="q" c="90" ts="2509080418" ts-tts="25-09-08 04:18:45.996" />
      <m id="r24394397" t="d" c="64" ts="2509081149" ts-tts="25-09-08 11:49:53.110" />
      <m id="r24394399" t="d" c="64" ts="2509081149" ts-tts="25-09-08 11:49:53.110" />
      <m id="r24394400" t="d" c="64" ts="2509081149" ts-tts="25-09-08 11:49:53.110" />
      <m id="r24394402" t="d" c="64" ts="2509081149" ts-tts="25-09-08 11:49:53.110" />
      <m id="r24394403" t="d" c="64" ts="2509081149" ts-tts="25-09-08 11:49:53.110" />
      <m id="r24394405" t="d" c="64" ts="2509081149" ts-tts="25-09-08 11:49:53.110" />
      <m id="r24394406" t="d" c="64" ts="2509081149" ts-tts="25-09-08 11:49:53.110" />
      <m id="r24394408" t="d" c="64" ts="2509081149" ts-tts="25-09-08 11:49:53.110" />
      <m id="r24436821" t="f" c="0" ts="2509081602" ts-tts="25-09-08 16:02:22.617" />
      <m id="r24436822" t="f" c="0" ts="2509081602" ts-tts="25-09-08 16:02:22.617" />
      <m id="r24436823" t="f" c="0" ts="2509081602" ts-tts="25-09-08 16:02:22.617" />
      <m id="r24436824" t="f" c="0" ts="2509081602" ts-tts="25-09-08 16:02:22.617" />
      <m id="r24437047" t="f" c="0" ts="2509081603" ts-tts="25-09-08 16:03:26.423" />
    </ar>
    <dp ppth="Berlin Ostbahnhof" pp="12" ct="2509081659" pt="2509081621" hi="1">
      <m id="r24341989" t="q" c="90" ts="2509080418" ts-tts="25-09-08 04:18:45.996" />
      <m id="r24341991" t="q" c="90" ts="2509080418" ts-tts="25-09-08 04:18:45.996" />
      <m id="r24394397" t="d" c="64" ts="2509081149" ts-tts="25-09-08 11:49:53.110" />
      <m id="r24394399" t="d" c="64" ts="2509081149" ts-tts="25-09-08 11:49:53.110" />
      <m id="r24394400" t="d" c="64" ts="2509081149" ts-tts="25-09-08 11:49:53.110" />
      <m id="r24394402" t="d" c="64" ts="2509081149" ts-tts="25-09-08 11:49:53.110" />
      <m id="r24394403" t="d" c="64" ts="2509081149" ts-tts="25-09-08 11:49:53.110" />
      <m id="r24394405" t="d" c="64" ts="2509081149" ts-tts="25-09-08 11:49:53.110" />
      <m id="r24394406" t="d" c="64" ts="2509081149" ts-tts="25-09-08 11:49:53.110" />
      <m id="r24394408" t="d" c="64" ts="2509081149" ts-tts="25-09-08 11:49:53.110" />
      <m id="r24437047" t="f" c="0" ts="2509081603" ts-tts="25-09-08 16:03:26.423" />
    </dp>
    <tl f="F" t="p" o="80" c="ICE" n="849" />
  </s>
  <s id="6209522400545496804-2509080906-14" eva="8011160">
    <m id="r2488158" t="h" from="2509081015" to="2509082000" cat="Störung" ts="2509081042" ts-tts="25-09-08 19:16:04.557" pr="1" />
    <m id="r982443329" t="c" ts="2509081457" ts-tts="25-09-08 14:57:09.016" />
    <m id="r982443331" t="c" ts="2509081457" ts-tts="25-09-08 14:57:09.016" />
    <m id="r982443604alt" t="c" ts="2509081519" ts-tts="25-09-08 15:19:07.373" />
    <m id="r982443328" t="c" ts="2509081457" ts-tts="25-09-08 14:57:09.016" />
    <m id="r982443326" t="c" ts="2509081457" ts-tts="25-09-08 14:57:09.016" />
    <ar ct="2509081510">
      <m id="r24381216" t="d" c="43" ts="2509081032" ts-tts="25-09-08 10:32:27.586" />
      <m id="r24381218" t="d" c="43" ts="2509081032" ts-tts="25-09-08 10:32:27.586" />
      <m id="r24389621" t="f" c="0" ts="2509081122" ts-tts="25-09-08 11:23:06.330" />
      <m id="r24389622" t="f" c="0" ts="2509081122" ts-tts="25-09-08 11:23:06.330" />
      <m id="r24394803" t="d" c="64" ts="2509081151" ts-tts="25-09-08 11:51:27.530" />
      <m id="r24418052" t="f" c="0" ts="2509081415" ts-tts="25-09-08 14:15:56.661" />
      <m id="r24424351" t="f" c="0" ts="2509081457" ts-tts="25-09-08 14:57:25.126" />
    </ar>
    <dp ct="2509081514">
      <m id="r24381216" t="d" c="43" ts="2509081032" ts-tts="25-09-08 10:32:27.586" />
      <m id="r24381218" t="d" c="43" ts="2509081032" ts-tts="25-09-08 10:32:27.586" />
      <m id="r24389621" t="f" c="0" ts="2509081122" ts-tts="25-09-08 11:23:06.330" />
      <m id="r24389622" t="f" c="0" ts="2509081122" ts-tts="25-09-08 11:23:06.330" />
      <m id="r24394803" t="d" c="64" ts="2509081151" ts-tts="25-09-08 11:51:27.530" />
      <m id="r24418052" t="f" c="0" ts="2509081415" ts-tts="25-09-08 14:15:56.661" />
    </dp>
  </s>
  <s id="-5511541014003594580-2509081652-11" eva="8011160">
    <m id="r2415041" t="h" from="2505120800" to="2509202359" cat="Information" ts="2505112304" ts-tts="25-09-07 23:16:04.468" pr="3" />
    <m id="r2487909" t="h" from="2509081033" to="2509082128" cat="Information" ts="2509080257" ts-tts="25-09-08 02:57:41.536" pr="2" />
    <m id="r2488158" t="h" from="2509081015" to="2509082000" cat="Störung" ts="2509081042" ts-tts="25-09-08 19:16:04.557" pr="1" />
    <m id="r2488379" t="h" from="2509081652" to="2509082128" cat="Information" ts="2509081810" ts-tts="25-09-08 18:10:23.039" pr="2" />
    <ar ct="2509082138">
      <m id="r24339869" t="q" c="98" ts="2509080255" ts-tts="25-09-08 02:55:54.846" />
      <m id="r24339871" t="q" c="98" ts="2509080255" ts-tts="25-09-08 02:55:54.846" />
      <m id="r24339877" t="f" c="0" ts="2509080255" ts-tts="25-09-08 02:56:10.102" />
      <m id="r24454433" t="d" c="43" ts="2509081744" ts-tts="25-09-08 17:44:21.429" />
      <m id="r24454435" t="d" c="43" ts="2509081744" ts-tts="25-09-08 17:44:21.429" />
      <m id="r24454437" t="d" c="43" ts="2509081744" ts-tts="25-09-08 17:44:21.429" />
      <m id="r24458337" t="q" c="85" ts="2509081810" ts-tts="25-09-08 18:10:39.454" />
      <m id="r24458339" t="q" c="85" ts="2509081810" ts-tts="25-09-08 18:10:39.454" />
      <m id="r24460109" t="f" c="0" ts="2509081821" ts-tts="25-09-08 18:21:33.905" />
    </ar>
    <dp ct="2509082141">
      <m id="r24339869" t="q" c="98" ts="2509080255" ts-tts="25-09-08 02:55:54.846" />
      <m id="r24339871" t="q" c="98" ts="2509080255" ts-tts="25-09-08 02:55:54.846" />
      <m id="r24339877" t="f" c="0" ts="2509080255" ts-tts="25-09-08 02:56:10.102" />
      <m id="r24454433" t="d" c="43" ts="2509081744" ts-tts="25-09-08 17:44:21.429" />
      <m id="r24454435" t="d" c="43" ts="2509081744" ts-tts="25-09-08 17:44:21.429" />
      <m id="r24454437" t="d" c="43" ts="2509081744" ts-tts="25-09-08 17:44:21.429" />
      <m id="r24458337" t="q" c="85" ts="2509081810" ts-tts="25-09-08 18:10:39.454" />
      <m id="r24458339" t="q" c="85" ts="2509081810" ts-tts="25-09-08 18:10:39.454" />
      <m id="r24460109" t="f" c="0" ts="2509081821" ts-tts="25-09-08 18:21:33.905" />
    </dp>
  </s>
  <s id="7188954872564278301-2509081451-10" eva="8011160">
    <m id="r2415041" t="h" from="2505120800" to="2509202359" cat="Information" ts="2505112304" ts-tts="25-09-07 23:16:04.468" pr="3" />
    <m id="r2487908" t="h" from="2509080349" to="2509081927" cat="Information" ts="2509080253" ts-tts="25-09-08 02:53:37.310" pr="3" />
    <m id="r2488158" t="h" from="2509081015" to="2509082000" cat="Störung" ts="2509081042" ts-tts="25-09-08 19:16:04.557" pr="1" />
    <m id="r982447086" t="c" ts="2509081913" ts-tts="25-09-08 19:13:13.888" />
    <m id="r982447087" t="c" ts="2509081913" ts-tts="25-09-08 19:13:13.888" />
    <m id="r982447088" t="c" ts="2509081913" ts-tts="25-09-08 19:13:13.888" />
    <ar ct="2509081928">
      <m id="r24339823" t="q" c="98" ts="2509080251" ts-tts="25-09-08 02:51:35.340" />
      <m id="r24339825" t="q" c="98" ts="2509080251" ts-tts="25-09-08 02:51:35.340" />
      <m id="r24385992" t="q" c="82" ts="2509081101" ts-tts="25-09-08 11:01:50.185" />
      <m id="r24385995" t="q" c="82" ts="2509081101" ts-tts="25-09-08 11:01:50.185" />
      <m id="r24463616" t="d" c="43" ts="2509081849" ts-tts="25-09-08 18:49:24.394" />
      <m id="r24463618" t="d" c="43" ts="2509081849" ts-tts="25-09-08 18:49:24.394" />
      <m id="r24463620" t="d" c="43" ts="2509081849" ts-tts="25-09-08 18:49:24.394" />
      <m id="r24466913" t="f" c="0" ts="2509081913" ts-tts="25-09-08 19:13:14.027" />
    </ar>
    <dp ct="2509081931">
      <m id="r24339823" t="q" c="98" ts="2509080251" ts-tts="25-09-08 02:51:35.340" />
      <m id="r24339825" t="q" c="98" ts="2509080251" ts-tts="25-09-08 02:51:35.340" />
      <m id="r24385992" t="q" c="82" ts="2509081101" ts-tts="25-09-08 11:01:50.185" />
      <m id="r24385995" t="q" c="82" ts="2509081101" ts-tts="25-09-08 11:01:50.185" />
      <m id="r24463616" t="d" c="43" ts="2509081849" ts-tts="25-09-08 18:49:24.394" />
      <m id="r24463618" t="d" c="43" ts="2509081849" ts-tts="25-09-08 18:49:24.394" />
      <m id="r24463620" t="d" c="43" ts="2509081849" ts-tts="25-09-08 18:49:24.394" />
    </dp>
  </s>
  <s id="7127812590731908748-2509080945-8" eva="8011160">
    <m id="r2415041" t="h" from="2505120800" to="2509202359" cat="Information" ts="2505112304" ts-tts="25-09-07 23:16:04.468" pr="3" />
    <m id="r2488232" t="h" from="2509080945" to="2509081428" cat="Information" ts="2509081304" ts-tts="25-09-08 13:04:23.897" pr="2" />
    <m id="r2488158" t="h" from="2509081015" to="2509082000" cat="Störung" ts="2509081042" ts-tts="25-09-08 19:16:04.557" pr="1" />
    <m id="r982442768" t="c" ts="2509081416" ts-tts="25-09-08 14:16:12.318" />
    <m id="r982442763" t="c" ts="2509081416" ts-tts="25-09-08 14:16:12.318" />
    <m id="r982442772" t="c" ts="2509081416" ts-tts="25-09-08 14:16:12.319" />
    <m id="r982442766" t="c" ts="2509081416" ts-tts="25-09-08 14:16:12.318" />
    <m id="r982442775" t="c" ts="2509081416" ts-tts="25-09-08 14:16:12.319" />
    <ar ct="2509081430">
      <m id="r24390520" t="d" c="43" ts="2509081129" ts-tts="25-09-08 11:29:39.481" />
      <m id="r24390522" t="d" c="43" ts="2509081129" ts-tts="25-09-08 11:29:39.481" />
      <m id="r24405550" t="q" c="83" ts="2509081303" ts-tts="25-09-08 13:03:52.258" />
      <m id="r24405554" t="q" c="83" ts="2509081303" ts-tts="25-09-08 13:03:52.258" />
    </ar>
    <dp ct="2509081433">
      <m id="r24390520" t="d" c="43" ts="2509081129" ts-tts="25-09-08 11:29:39.481" />
      <m id="r24390522" t="d" c="43" ts="2509081129" ts-tts="25-09-08 11:29:39.481" />
      <m id="r24405550" t="q" c="83" ts="2509081303" ts-tts="25-09-08 13:03:52.258" />
      <m id="r24405554" t="q" c="83" ts="2509081303" ts-tts="25-09-08 13:03:52.258" />
    </dp>
  </s>
  <s id="-8906112445839706377-2509080919-10" eva="8011160">
    <m id="r2415041" t="h" from="2505120800" to="2509202359" cat="Information" ts="2505112304" ts-tts="25-09-07 23:16:04.468" pr="3" />
    <m id="r2488158" t="h" from="2509081015" to="2509082000" cat="Störung" ts="2509081042" ts-tts="25-09-08 19:16:04.557" pr="1" />
    <m id="r982442769" t="c" ts="2509081416" ts-tts="25-09-08 14:16:12.318" />
    <m id="r982442762" t="c" ts="2509081416" ts-tts="25-09-08 14:16:12.318" />
    <m id="r982442774" t="c" ts="2509081416" ts-tts="25-09-08 14:16:12.319" />
    <m id="r982442767" t="c" ts="2509081416" ts-tts="25-09-08 14:16:12.318" />
    <m id="r982442765" t="c" ts="2509081416" ts-tts="25-09-08 14:16:12.318" />
    <ar ct="2509081430">
      <m id="r24375977" t="d" c="43" ts="2509080953" ts-tts="25-09-08 09:53:26.556" />
      <m id="r24375979" t="d" c="43" ts="2509080953" ts-tts="25-09-08 09:53:26.556" />
      <m id="r24375981" t="d" c="43" ts="2509080953" ts-tts="25-09-08 09:53:26.556" />
      <m id="r24381762" t="d" c="64" ts="2509081034" ts-tts="25-09-08 10:34:33.773" />
      <m id="r24381764" t="d" c="64" ts="2509081034" ts-tts="25-09-08 10:34:33.773" />
      <m id="r24381765" t="d" c="64" ts="2509081034" ts-tts="25-09-08 10:34:33.773" />
      <m id="r24381767" t="d" c="64" ts="2509081034" ts-tts="25-09-08 10:34:33.773" />
      <m id="r24381768" t="d" c="64" ts="2509081034" ts-tts="25-09-08 10:34:33.773" />
      <m id="r24381770" t="d" c="64" ts="2509081034" ts-tts="25-09-08 10:34:33.773" />
      <m id="r24381771" t="d" c="64" ts="2509081034" ts-tts="25-09-08 10:34:33.773" />
      <m id="r24381773" t="d" c="64" ts="2509081034" ts-tts="25-09-08 10:34:33.773" />
      <m id="r24390518" t="d" c="43" ts="2509081129" ts-tts="25-09-08 11:29:39.480" />
      <m id="r24405558" t="q" c="83" ts="2509081303" ts-tts="25-09-08 13:03:52.258" />
      <m id="r24405563" t="q" c="83" ts="2509081303" ts-tts="25-09-08 13:03:52.258" />
    </ar>
    <dp ct="2509081436">
      <m id="r24375977" t="d" c="43" ts="2509080953" ts-tts="25-09-08 09:53:26.556" />
      <m id="r24375979" t="d" c="43" ts="2509080953" ts-tts="25-09-08 09:53:26.556" />
      <m id="r24375981" t="d" c="43" ts="2509080953" ts-tts="25-09-08 09:53:26.556" />
      <m id="r24381762" t="d" c="64" ts="2509081034" ts-tts="25-09-08 10:34:33.773" />
      <m id="r24381764" t="d" c="64" ts="2509081034" ts-tts="25-09-08 10:34:33.773" />
      <m id="r24381765" t="d" c="64" ts="2509081034" ts-tts="25-09-08 10:34:33.773" />
      <m id="r24381767" t="d" c="64" ts="2509081034" ts-tts="25-09-08 10:34:33.773" />
      <m id="r24381768" t="d" c="64" ts="2509081034" ts-tts="25-09-08 10:34:33.773" />
      <m id="r24381770" t="d" c="64" ts="2509081034" ts-tts="25-09-08 10:34:33.773" />
      <m id="r24381771" t="d" c="64" ts="2509081034" ts-tts="25-09-08 10:34:33.773" />
      <m id="r24381773" t="d" c="64" ts="2509081034" ts-tts="25-09-08 10:34:33.773" />
      <m id="r24390518" t="d" c="43" ts="2509081129" ts-tts="25-09-08 11:29:39.480" />
      <m id="r24405558" t="q" c="83" ts="2509081303" ts-tts="25-09-08 13:03:52.258" />
      <m id="r24405563" t="q" c="83" ts="2509081303" ts-tts="25-09-08 13:03:52.258" />
    </dp>
  </s>
  <s id="4447890004106418758-2509081852-11" eva="8011160">
    <m id="r2415041" t="h" from="2505120800" to="2509202359" cat="Information" ts="2505112304" ts-tts="25-09-07 23:16:04.468" pr="3" />
    <m id="r2488158" t="h" from="2509081015" to="2509082000" cat="Störung" ts="2509081042" ts-tts="25-09-08 19:16:04.556" pr="1" />
    <ar ct="2509082317" />
    <dp ct="2509082320" />
  </s>
  <s id="-130190603183544299-2509081600-13" eva="8011160">
    <m id="r2488090" t="h" from="2509080000" to="2512132359" cat="Information" ts="2509080941" ts-tts="25-09-08 09:41:52.299" pr="1" />
    <ar ct="2509082148" />
    <dp ct="2509082153" />
  </s>
  <s id="6365385521946896242-2509080920-25" eva="8011160">
    <m id="r2488085" t="h" from="2509080000" to="2512132359" cat="Information" ts="2509080935" ts-tts="25-09-08 09:35:19.872" pr="1" />
    <ar ct="2509081916">
      <m id="r24259207" t="d" c="13" ts="2509071119" ts-tts="25-09-07 11:19:44.412" />
      <m id="r24259209" t="d" c="13" ts="2509071119" ts-tts="25-09-07 11:19:44.412" />
      <m id="r24259210" t="d" c="13" ts="2509071119" ts-tts="25-09-07 11:19:44.412" />
      <m id="r24259212" t="d" c="13" ts="2509071119" ts-tts="25-09-07 11:19:44.412" />
      <m id="r24259213" t="d" c="13" ts="2509071119" ts-tts="25-09-07 11:19:44.412" />
      <m id="r24259215" t="d" c="13" ts="2509071119" ts-tts="25-09-07 11:19:44.412" />
      <m id="r24259216" t="d" c="13" ts="2509071119" ts-tts="25-09-07 11:19:44.412" />
      <m id="r24259218" t="d" c="13" ts="2509071119" ts-tts="25-09-07 11:19:44.412" />
      <m id="r24259219" t="d" c="13" ts="2509071119" ts-tts="25-09-07 11:19:44.412" />
      <m id="r24259221" t="d" c="13" ts="2509071119" ts-tts="25-09-07 11:19:44.412" />
    </ar>
  </s>
  <s id="5254069718021379768-2509081400-13" eva="8011160">
    <m id="r2488241" t="h" from="2509081400" to="2509082002" cat="Information" ts="2509081327" ts-tts="25-09-08 13:27:52.595" pr="2" />
    <m id="r2488090" t="h" from="2509080000" to="2512132359" cat="Information" ts="2509080941" ts-tts="25-09-08 09:41:52.299" pr="1" />
    <ar ct="2509081958">
      <m id="r24452411" t="q" c="98" ts="2509081730" ts-tts="25-09-08 17:31:04.967" />
      <m id="r24452413" t="q" c="98" ts="2509081730" ts-tts="25-09-08 17:31:04.967" />
      <m id="r24463689" t="d" c="31" ts="2509081850" ts-tts="25-09-08 18:50:11.606" />
      <m id="r24463691" t="d" c="31" ts="2509081850" ts-tts="25-09-08 18:50:11.606" />
    </ar>
    <dp ct="2509082001">
      <m id="r24452411" t="q" c="98" ts="2509081730" ts-tts="25-09-08 17:31:04.967" />
      <m id="r24452413" t="q" c="98" ts="2509081730" ts-tts="25-09-08 17:31:04.967" />
      <m id="r24463689" t="d" c="31" ts="2509081850" ts-tts="25-09-08 18:50:11.606" />
      <m id="r24463691" t="d" c="31" ts="2509081850" ts-tts="25-09-08 18:50:11.606" />
    </dp>
  </s>
  <s id="-7508358264308364137-2509081714-22" eva="8011160">
    <m id="r2483170" t="h" from="2509080000" to="2509121900" cat="Information" ts="2509072309" ts-tts="25-09-07 23:09:53.505" pr="2" />
    <ar ct="2509081912" l="7" />
    <dp ct="2509081914" l="7" />
  </s>
  <s id="-8117698018396659816-2509081712-14" eva="8011160">
    <ar ct="2509081914" l="1" />
    <dp ct="2509081916" l="1">
      <m id="r24463714" t="f" c="0" ts="2509081850" ts-tts="25-09-08 18:50:11.606" />
      <m id="r24464184" t="f" c="0" ts="2509081853" ts-tts="25-09-08 18:53:22.014" />
    </dp>
  </s>
  <s id="8953942811272684056-2509081814-22" eva="8011160">
    <m id="r2483170" t="h" from="2509080000" to="2509121900" cat="Information" ts="2509072309" ts-tts="25-09-07 23:09:53.505" pr="2" />
    <ar ct="2509082015" l="7" />
    <dp ct="2509082016" l="7" />
  </s>
  <m id="i1084275" t="i" from="2509051600" to="2509052240" ts="2509051718" ts-tts="25-09-05 17:18:48.013" />
</timetable>