<?xml version='1.0' encoding='utf-8'?>
<timetable station="Berlin-Johannisthal" eva="8089007">
  <s id="1160641199814617012-2509042337-7" eva="8089007">
    <ar ct="2509050000" l="45" />
    <dp ct="2509050000" l="45" />
  </s>
  <s id="665427122274433924-2509050015-7" eva="8089007">
    <ar cpth="Berlin Treptower Park|Berlin Plänterwald|Berlin Baumschulenweg|Berlin-Schöneweide (S)" ct="2509050030" l="8" />
    <dp cpth="Berlin-Adlershof|Berlin-Grünau" ct="2509050031" l="8" />
  </s>
</timetable>