<?xml version='1.0' encoding='utf-8'?>
<timetable station="Berlin-Lichtenberg" eva="8010036">
  <s id="-1339822737109526379-2509090038-1" eva="8010036">
    <dp cpth="" cs="c" clt="2509080153" l="26">
      <m id="r24027623" t="f" c="1000" ts="2509051011" ts-tts="25-09-05 10:11:25.470" />
      <m id="r24127796" t="f" c="1000" ts="2509060151" ts-tts="25-09-06 01:51:09.463" />
      <m id="r24238747" t="f" c="1000" ts="2509070150" ts-tts="25-09-07 01:50:07.800" />
      <m id="r24337381" t="f" c="1000" ts="2509080150" ts-tts="25-09-08 01:50:44.469" />
      <m id="r24339160" t="d" c="49" ts="2509080237" ts-tts="25-09-08 02:37:27.834" />
      <m id="r24339162" t="d" c="49" ts="2509080237" ts-tts="25-09-08 02:37:27.834" />
      <m id="r24339164" t="d" c="49" ts="2509080237" ts-tts="25-09-08 02:37:27.834" />
      <m id="r24339166" t="d" c="49" ts="2509080237" ts-tts="25-09-08 02:37:27.834" />
      <m id="r24339168" t="d" c="49" ts="2509080237" ts-tts="25-09-08 02:37:27.834" />
      <m id="r24339170" t="d" c="49" ts="2509080237" ts-tts="25-09-08 02:37:27.834" />
      <m id="r24339172" t="d" c="49" ts="2509080237" ts-tts="25-09-08 02:37:27.834" />
      <m id="r24339174" t="d" c="49" ts="2509080237" ts-tts="25-09-08 02:37:27.834" />
      <m id="r24339176" t="d" c="49" ts="2509080237" ts-tts="25-09-08 02:37:27.834" />
      <m id="r24339178" t="d" c="49" ts="2509080237" ts-tts="25-09-08 02:37:27.834" />
      <m id="r24339180" t="d" c="49" ts="2509080237" ts-tts="25-09-08 02:37:27.834" />
      <m id="r24339182" t="d" c="49" ts="2509080237" ts-tts="25-09-08 02:37:27.834" />
    </dp>
  </s>
  <s id="-2462281602049893729-2509080814-1" eva="8010036">
    <dp ct="2509080815" l="32" />
  </s>
  <m id="i1084275" t="i" from="2509051600" to="2509052240" ts="2509051718" ts-tts="25-09-05 17:18:40.825" />
</timetable>