<?xml version='1.0' encoding='utf-8'?>
<timetable station="Berlin Südkreuz" eva="8011113">
  <s id="919585816458009806-2509071712-5" eva="8011113">
    <ar l="35">
      <m id="r24193510" t="f" c="1000" ts="2509061606" ts-tts="25-09-06 16:06:22.864" />
      <m id="r24214147" t="f" c="0" ts="2509061909" ts-tts="25-09-06 19:09:55.359" />
      <m id="r24223797" t="q" c="95" ts="2509062044" ts-tts="25-09-06 20:44:04.517" />
    </ar>
    <dp l="35">
      <m id="r24193510" t="f" c="1000" ts="2509061606" ts-tts="25-09-06 16:06:22.864" />
      <m id="r24214147" t="f" c="0" ts="2509061909" ts-tts="25-09-06 19:09:55.359" />
      <m id="r24223797" t="q" c="95" ts="2509062044" ts-tts="25-09-06 20:44:04.517" />
    </dp>
  </s>
  <s id="5950655788274726626-2509071735-7" eva="8011113">
    <m id="r2471136" t="h" from="2509010000" to="2509302300" cat="Information" ts="2508312308" ts-tts="25-09-06 23:16:03.375" pr="2" />
    <m id="r2484847" t="h" from="2509011500" to="2509192359" cat="Information" ts="2509011714" ts-tts="25-09-06 23:16:03.517" pr="2" />
  </s>
  <s id="277859891258251921-2509071742-3" eva="8011113">
    <m id="r2473869" t="h" from="2508170000" to="2512072359" cat="Information" ts="2508172308" ts-tts="25-09-06 23:16:03.380" pr="2" />
  </s>
  <s id="3243926568790461754-2509071703-1" eva="8011113">
    <m id="r2458360" t="h" from="2508020000" to="2512132359" cat="Information" ts="2508022307" ts-tts="25-09-06 23:16:03.192" pr="1" />
  </s>
  <s id="-2309088386611741789-2509071713-1" eva="8011113">
    <m id="r2415041" t="h" from="2505120800" to="2509202359" cat="Information" ts="2505112304" ts-tts="25-09-06 23:16:03.171" pr="3" />
  </s>
  <s id="-4831004071712342153-2509071701-24" eva="8011113">
    <m id="r2333137" t="h" from="2412150000" to="2510242358" cat="Information" ts="2412142302" ts-tts="25-09-06 23:16:03.154" pr="2" />
  </s>
  <s id="5833177948138978538-2509071735-1" eva="8011113">
    <m id="r2333137" t="h" from="2412150000" to="2510242358" cat="Information" ts="2412142302" ts-tts="25-09-06 23:16:03.154" pr="2" />
  </s>
  <s id="-1816033555238499772-2509071103-14" eva="8011113">
    <ar l="3">
      <m id="r24237900" t="f" c="0" ts="2509070115" ts-tts="25-09-07 01:15:55.163" />
    </ar>
    <dp l="3">
      <m id="r24237900" t="f" c="0" ts="2509070115" ts-tts="25-09-07 01:15:55.163" />
    </dp>
  </s>
  <m id="i1084275" t="i" from="2509051600" to="2509052240" ts="2509051718" ts-tts="25-09-05 17:18:48.013" />
</timetable>