<?xml version='1.0' encoding='utf-8'?>
<timetable station="Berlin-Zehlendorf" eva="8089098">
  <s id="-377270736863598262-2509022234-5" eva="8089098">
    <ar ct="2509022243" l="1" />
    <dp ct="2509022243" l="1" />
  </s>
  <s id="2513311440812336079-2509022214-5" eva="8089098">
    <ar ct="2509022226" l="1" />
    <dp ct="2509022226" l="1" />
  </s>
  <s id="1927254637949588586-2509022211-31" eva="8089098">
    <ar ct="2509022323" l="1" />
    <dp ct="2509022324" l="1" />
  </s>
  <s id="-2325864418383507047-2509022233-1" eva="8089098">
    <dp ct="2509022233" l="1" />
  </s>
  <s id="-6091415033923146068-2509022231-31" eva="8089098">
    <ar ct="2509022342" l="1" />
    <dp ct="2509022342" l="1" />
  </s>
  <s id="2701630335414592991-2509022204-5" eva="8089098">
    <ar ct="2509022214" l="1" />
    <dp ct="2509022214" l="1" />
  </s>
  <s id="7968467923673819784-2509022118-26" eva="8089098">
    <ar ct="2509022212" l="1" />
  </s>
</timetable>